Workbook

Sheet README
A1: Mech Arena Database — How To Read This Sheet
A3: This workbook is the community-verified database that powers ArenaBot. It's split into 10 tabs. The four "stat" tabs (Mechs, Weapons, Pilots, Mods) hold identity and gameplay info — one row per item. The four "Upgrade Costs" tabs are shared reference tables — one row per rarity tier per upgrade step, not per item, because the game charges the same upgrade cost to every item of the same rarity (and, for weapons, the same energy level).
A5: TAB-BY-TAB GUIDE
A7: Mechs | B7: One row per mech (46 total). Stats, ability, strengths/weaknesses, and Unlock Cost — what it costs to unlock the mech itself, separate from upgrading it afterward.
A8: Weapons | B8: One row per weapon energy variant (251 total). E.g. "Storm Rack" appears as several rows — Storm Rack 6, Storm Rack 8, Storm Rack 12 — because each energy version has different stats and a different unlock cost. "Base Name" groups the variants together.
A9: Pilots | B9: One row per pilot (36 total). Skill/weapon specialty and the HP/DMG % bonus they grant.
A10: Mods | B10: One row per mod (14 total). Effect description and base purchase cost.
A12: Mech Upgrade Costs | B12: How much it costs to level up a mech from Star X Level Y to the next step — Credits, A-Coins, and Blueprints needed. This is NOT one row per mech — it's one row per rarity tier (7 tiers) per star/level (42 steps) = 294 rows, because a Common mech and every other Common mech cost the same to upgrade.
A13: Weapon Upgrade Costs | B13: Same idea as above but for weapons — one row per rarity+energy combination (37 of them) per star/level step = 1,554 rows.
A14: Pilot Upgrade Costs | B14: Same idea — one row per rarity (Rare/Epic/Legendary) per star/level step. Costs are in A-Coins, Marks, and XP instead of Credits/Blueprints.
A15: Mod Upgrade Costs | B15: One row per mod per level (2 through 6). Costs are in Basic Mod Parts and Elite Mod Parts.
A17: Best Builds | B17: Community-submitted mech + weapon loadouts.
A18: Meta | B18: The current top-ranked builds, in order.
A20: HOW TO LOOK UP AN UPGRADE COST — WORKED EXAMPLE
A22: Say you want to know what it costs to upgrade Aegis to Star 2, Level 1.
A23: Step 1 — Go to the Mechs tab, find "Aegis", and read its Rarity Key column. It says: epic_b_mech
A24: Step 2 — Go to the Mech Upgrade Costs tab. Filter/search for Rarity Key = epic_b_mech AND Star = 2 AND Level = 1.
A25: Step 3 — That row shows the Credits, A-Coins, and Blueprints needed for that single step.
A27: Weapons work the same way, just with the Weapon's Rarity Key (which also encodes energy, e.g. epic_b_weapon_6) against the Weapon Upgrade Costs tab.
A29: Mods work the same way using the Cost Table Key column on the Mods tab (e.g. epic_perimeter_ml) against the Mod Upgrade Costs tab.
A31: WHAT THE "RARITY KEY" / "COST TABLE KEY" COLUMNS MEAN
A33: These are just the item's Rarity (and Energy, for weapons) written in one lowercase, underscore-joined string — it exists purely so this key can be matched exactly against the Upgrade Costs tabs. You never need to type or edit it; it's generated from the Rarity and Energy columns already on that row.
A35: ABBREVIATIONS
A37: A-Coins | B37: In-game premium-ish currency (sometimes shown as "ACoins").
A38: Credits | B38: Basic in-game currency, earned freely through play.
A39: Blueprints | B39: Item-specific currency needed (alongside Credits) to star-up a mech or weapon.
A40: Marks | B40: Pilot-upgrade currency.
A41: XP | B41: Pilot experience points, spent on pilot leveling.
A42: Basic / Elite Mod Parts | B42: Currencies used to level up mods.
A43: Star / Level | B43: Mech Arena's two-axis upgrade system — an item levels up (1→Max) within a Star, then Star-ups reset the level and raise the power ceiling.
A45: DATA QUALITY NOTES
A47: Mechs, Weapons, and all four Upgrade Costs tabs come directly from the official community database (mecharenadev.com) and are treated as verified/authoritative.
A48: Pilots and Mods are filled in manually by the team. Check the "Verified" column on those two tabs before trusting a row — "Pending" or "Needs Review" means it hasn't been confirmed in-game yet. A few Mods rows are still blank (e.g. Perimeter's effect description) and are waiting on someone to fill them in.

Sheet Calculator
A1: Upgrade Cost Calculator
A2: Pick an item and a From/To Star+Level (or From/To Level for Mods). Totals below update automatically. Grey input cells are the only cells you should edit.
A4: MECH UPGRADE CALCULATOR
A5: Mech name
A6: From Star | B6: 1 | C6: From Level | D6: 1
A7: To Star | B7: 1 | C7: To Level | D7: 2
A8: Matched rarity key | B8: =IFERROR(INDEX(Mechs!$R$2:$R$47,MATCH(B5,Mechs!$B$2:$B$47,0)),"not found")
A9: TOTAL NEEDED | B9: Credits | C9: A-Coins | D9: Blueprints
B10: =SUMIFS('Mech Upgrade Costs'!$D$2:$D$295,'Mech Upgrade Costs'!$A$2:$A$295,B8,'Mech Upgrade Costs'!$G$2:$G$295,">"&((B6-1)*7+D6),'Mech Upgrade Costs'!$G$2:$G$295,"<="&((B7-1)*7+D7)) | C10: =SUMIFS('Mech Upgrade Costs'!$E$2:$E$295,'Mech Upgrade Costs'!$A$2:$A$295,B8,'Mech Upgrade Costs'!$G$2:$G$295,">"&((B6-1)*7+D6),'Mech Upgrade Costs'!$G$2:$G$295,"<="&((B7-1)*7+D7)) | D10: =SUMIFS('Mech Upgrade Costs'!$F$2:$F$295,'Mech Upgrade Costs'!$A$2:$A$295,B8,'Mech Upgrade Costs'!$G$2:$G$295,">"&((B6-1)*7+D6),'Mech Upgrade Costs'!$G$2:$G$295,"<="&((B7-1)*7+D7))
A12: WEAPON UPGRADE CALCULATOR
A13: Weapon name (incl. energy)
A14: From Star | B14: 1 | C14: From Level | D14: 1
A15: To Star | B15: 1 | C15: To Level | D15: 2
A16: Matched rarity key | B16: =IFERROR(INDEX(Weapons!$AE$2:$AE$252,MATCH(B13,Weapons!$B$2:$B$252,0)),"not found")
A17: TOTAL NEEDED | B17: Credits | C17: A-Coins | D17: Blueprints
B18: =SUMIFS('Weapon Upgrade Costs'!$D$2:$D$1555,'Weapon Upgrade Costs'!$A$2:$A$1555,B16,'Weapon Upgrade Costs'!$G$2:$G$1555,">"&((B14-1)*7+D14),'Weapon Upgrade Costs'!$G$2:$G$1555,"<="&((B15-1)*7+D15)) | C18: =SUMIFS('Weapon Upgrade Costs'!$E$2:$E$1555,'Weapon Upgrade Costs'!$A$2:$A$1555,B16,'Weapon Upgrade Costs'!$G$2:$G$1555,">"&((B14-1)*7+D14),'Weapon Upgrade Costs'!$G$2:$G$1555,"<="&((B15-1)*7+D15)) | D18: =SUMIFS('Weapon Upgrade Costs'!$F$2:$F$1555,'Weapon Upgrade Costs'!$A$2:$A$1555,B16,'Weapon Upgrade Costs'!$G$2:$G$1555,">"&((B14-1)*7+D14),'Weapon Upgrade Costs'!$G$2:$G$1555,"<="&((B15-1)*7+D15))
A20: PILOT UPGRADE CALCULATOR
A21: Pilot name
A22: From Star | B22: 1 | C22: From Level | D22: 1
A23: To Star | B23: 1 | C23: To Level | D23: 2
A24: Matched rarity | B24: =LOWER(IFERROR(INDEX(Pilots!$C$2:$C$37,MATCH(B21,Pilots!$B$2:$B$37,0)),"not found"))
A25: TOTAL NEEDED | B25: A-Coins | C25: Marks | D25: XP
B26: =SUMIFS('Pilot Upgrade Costs'!$D$2:$D$127,'Pilot Upgrade Costs'!$A$2:$A$127,B24,'Pilot Upgrade Costs'!$G$2:$G$127,">"&((B22-1)*7+D22),'Pilot Upgrade Costs'!$G$2:$G$127,"<="&((B23-1)*7+D23)) | C26: =SUMIFS('Pilot Upgrade Costs'!$E$2:$E$127,'Pilot Upgrade Costs'!$A$2:$A$127,B24,'Pilot Upgrade Costs'!$G$2:$G$127,">"&((B22-1)*7+D22),'Pilot Upgrade Costs'!$G$2:$G$127,"<="&((B23-1)*7+D23)) | D26: =SUMIFS('Pilot Upgrade Costs'!$F$2:$F$127,'Pilot Upgrade Costs'!$A$2:$A$127,B24,'Pilot Upgrade Costs'!$G$2:$G$127,">"&((B22-1)*7+D22),'Pilot Upgrade Costs'!$G$2:$G$127,"<="&((B23-1)*7+D23))
A28: MOD UPGRADE CALCULATOR
A29: Mod name
A30: From Level | B30: 1 | C30: To Level | D30: 2
A31: Matched cost key | B31: =IFERROR(INDEX(Mods!$L$2:$L$15,MATCH(B29,Mods!$B$2:$B$15,0)),"not found")
A32: TOTAL NEEDED | B32: Basic Mod Parts | C32: Elite Mod Parts
B33: =SUMIFS('Mod Upgrade Costs'!$C$2:$C$71,'Mod Upgrade Costs'!$A$2:$A$71,B31,'Mod Upgrade Costs'!$B$2:$B$71,">"&B30,'Mod Upgrade Costs'!$B$2:$B$71,"<="&D30) | C33: =SUMIFS('Mod Upgrade Costs'!$D$2:$D$71,'Mod Upgrade Costs'!$A$2:$A$71,B31,'Mod Upgrade Costs'!$B$2:$B$71,">"&B30,'Mod Upgrade Costs'!$B$2:$B$71,"<="&D30)

Sheet Mechs
A1: Mech ID | B1: Name | C1: Rarity | D1: Role | E1: Tier | F1: Max HP | G1: Max Speed | H1: Max Energy | I1: Power | J1: Ability Name | K1: Ability Description | L1: Ability Stats | M1: Strengths | N1: Weaknesses | O1: Reasoning | P1: Unlock Cost | Q1: Unlock Currency | R1: Rarity Key
A2: M001 | B2: Aegis | C2: Epic B | D2: Tank | E2: A | F2: 215,100 | G2: 20 | H2: 24 | I2: 953 | J2: Dome Shield | K2: Circular dome blocking attacks and most abilities from outside and above. | L2: Ability Cooldown: 10 s | Ability Duration: 10 s | Dome Radius: 10 m | Dome Durability: 750,000 | M2: Protects the whole team. | N2: Medium speed. | O2: The dome is one of the strongest team-play abilities in the game, completely blocking incoming fire for the whole team. High HP for an Epic. Drops to A rather than S only because it requires coordination to use well. | P2: 1865 | Q2: A-Coins | R2: epic_b_mech
A3: M002 | B3: Arachnos | C3: Rare | D3: Support | E3: D | F3: 120,600 | G3: 14 | H3: 32 | I3: 762 | J3: Spider Turret | K3: Spider Turret — Deploys a small destructible turret that activates and attacks when an enemy approaches. | L3: Ability Cooldown: 22 s | Turret Damage: 351 | Turret Active Lifetime: 10 s | Arachnos Turret Range: 30 m | M3: High energy capacity; passive area denial. | N3: Slowest mech; negligible turret damage; very long cooldown; very low HP. | O3: Tied for the slowest mech in the game at 14 km/h, making it nearly immobile in dynamic fights. The turret deals trivial damage (351 at max), has a 22s cooldown, and can be destroyed instantly. High energy capacity is the only redeeming quality. | P3: 42200 | Q3: Credits | R3: rare_mech
A4: M003 | B4: Ares | C4: Rare | D4: Tank | E4: B | F4: 160,800 | G4: 18 | H4: 24 | I4: 857 | J4: Wide Shield | K4: Wide Shield — Activates a portable shield that protects the Mech and nearby allies from enemy fire. | L4: Ability Cooldown: 12 s | Shield Durability: 43,900 | M4: Shield covers allies; always active while up; good energy capacity. | N4: Lower HP than Epic/Legendary tanks; no offensive element. | O4: The team coverage sets Ares apart from Juggernaut — protecting allies as well as itself is meaningful in grouped play. Decent HP for a Rare and good energy. Held back by moderate durability and no offensive component. | P4: 420 | Q4: A-Coins | R4: rare_mech
A5: M004 | B5: Bastion | C5: Legendary | D5: Tank | E5: A | F5: 284,100 | G5: 18 | H5: 24 | I5: 1,083 | J5: Blast Shield | K5: Side shield that explodes and EMPs when destroyed. | L5: Ability Cooldown: 16 s | Shield Durability: 60,000 | Shield Damage Radius: 30 m | Blast Shield Damage: 22,700 | Blast Shield EMP Duration: 3 s | M5: Extremely high HP. | N5: Slow. | O5: Highest HP in the game and EMP on shield destruction. However, 18 km/h means it cannot reposition or contest objectives effectively — it is a static anchor that skilled opponents simply flank around. | P5: 9375 | Q5: A-Coins | R5: legendary_mech
A6: M005 | B6: Blizzfrost | C6: Legendary | D6: Scout | E6: S | F6: 181,800 | G6: 29 | H6: 24 | I6: 962 | J6: Icy Grip | K6: Icy Grip — Creates a freeze zone dealing damage. Frozen enemies cannot move; each frozen enemy reduces damage taken. Stasis immunity while active. | L6: Ability Cooldown: 7 s | Ability Duration: 5 s | Icy Grip Radius: 30 m | Icy Grip Damage: 50,000 | Speed Boost: +20% | DMG Reduction (Base): 50% | DMG Reduction (Per Mech): 12.5% | M6: Largest AoE of any scout; damage reduction scales per frozen enemy; Stasis immunity. | N6: None. | O6: One of the strongest abilities in the game. Massive 30m AoE, 50k damage, movement denial, and a damage reduction that stacks per frozen enemy — effectively near-immortal in team fights. Stasis immunity prevents the obvious counter. | Q6: Paid | R6: legendary_mech
A7: M006 | B7: Blockhorn | C7: Legendary | D7: Tank | E7: A | F7: 227,300 | G7: 19 | H7: 32 | I7: 948 | J7: Barricade | K7: Barricade — Deploys an impassable barrier blocking enemy fire and most abilities; boosts ally damage behind it. | L7: Ability Cooldown: 9 s | Ability Duration: 7 s | Barricade Durability: 503,100 | Barricade Amp Zone Damage: +30% | Barricade Amp Zone Size: 11.5 x 10 m² | M7: Impassable barrier; boosts ally damage; blocks most abilities; high energy cap. | N7: Static; can be flanked; requires team coordination. | O7: The Barricade has extraordinary durability (503k at max rank) and the Amp Zone behind it creates a powerful forward push position for teammates. High energy capacity and good HP for an Epic. Requires team coordination to fully exploit. | P7: 9375 | Q7: A-Coins | R7: legendary_mech
A8: M007 | B8: Brickhouse | C8: Legendary | D8: Support | E8: B | F8: 241,500 | G8: 14 | H8: 24 | I8: 1,033 | J8: Overcharger | K8: Overcharger — Boosts damage for self and nearby allies. | L8: Ability Cooldown: 12 s | Ability Duration: 10s | Mech Bonus Damage: +50% | Team Bonus Damage: +100% | Overcharger Radius: 10m | M8: Massive ally damage boost in radius; high HP. | N8: Slowest mech; tiny radius; team buff rarely applies in practice. | O8: The +100% team damage buff is among the strongest damage multipliers in the game but the 14 km/h speed and tiny 10m radius make it extremely difficult to apply to teammates in real matches. Usually only reliably buffs itself. | P8: 937500 | Q8: Credits | R8: legendary_mech
A9: M008 | B9: Cheetah | C9: Epic A | D9: Support | E9: D | F9: 131,400 | G9: 22 | H9: 16 | I9: 872 | J9: Mines | K9: Places up to 3 mines that explode when an enemy comes close. | L9: Ability Cooldown: 6 s | Ability Damage: 38,000 | Mine Damage Radius: 12 m | M9: Very high burst damage from mines. | N9: Relatively slow and not durable. Ability is easily avoidable when paying attention to the ground. | O9: Low HP, mid energy, mid speed. Strong damage ability but very easily avoidable. | P9: 1305 | Q9: A-Coins | R9: epic_a_mech
A10: M009 | B10: Citadel | C10: Legendary | D10: Support | E10: S | F10: 269,900 | G10: 19 | H10: 24 | I10: 1,066 | J10: Seismic Field | K10: Seismic Field — Creates a zone slowing and blocking movement of enemies. Citadel gains speed and a scaling shield. Reduces status effect duration on Citadel. | L10: Ability Cooldown: 10 s | Ability Duration: 8 s | Seismic Field Size: 20 x 13 m² | Citadel Shield Durability: 123,400 | Bonus Shield Durability: 47,500 | Enemy Speed Reduction: -60% | Citadel Speed Increase: +60% | Status Effect Reduction: -75% | M10: High HP support; slows enemies and blocks movement abilities; scaling shield; status effect resistance; speed boost during ability. | N10: Self-focused ability; needs enemies in zone for full shield value. | O10: One of the most layered support abilities in the game. High HP for a support, decent base speed that surges during ability, a massive self-scaling shield, enemy movement denial, and near-immunity to status effects. Excels in both team fights and 1v1. | Q10: Paid | R10: legendary_mech
A11: M010 | B11: Deathwalker | C11: Legendary | D11: Tank | E11: S | F11: 227,300 | G11: 19 | H11: 32 | I11: 948 | J11: Reanimate | K11: Sets a resurrect point, gains +60% speed. If destroyed while the ability is active it resurrects at the point it set with 105% of its HP before ability activation. Cooldown: 15s. | L11: Ability Cooldown: 15 s | Ability Duration: 15 s | Invulnerability Duration: 3 s | Speed Boost: +60% | HP Restoration: 5% | M11: Resurrection with speed boost is still a powerful defensive ability; strong HP and energy. | N11: Slow base speed without ability; 15s cooldown creates longer exposure windows; only restores 5% above pre-ability HP. | O11: Very effective at rushing directly into the enemy lines to deal massive burst damage at once before being reanimated.The resurrection is a strong safety net but the long cooldown means opponents have time to punish Deathwalker when it is on cooldown. | Q11: Paid | R11: legendary_mech
A12: M011 | B12: Dreadnought | C12: Legendary | D12: Attacker | E12: A | F12: 227,300 | G12: 22 | H12: 32 | I12: 948 | J12: Wipe Out | K12: Rocket line attack (33m long, 19.8m wide) with EMP; kill resets cooldown. | L12: Ability Cooldown: 9 s | Wipe Out EMP Duration: 2 s | Wipe Out Damage: 74,319 | Wipe Out Area Size: 19.8 x 33 m² | M12: Huge burst damage in a short time. | N12: Short EMP duration. | O12: Wide AoE, EMP, high HP, and a kill-reset mechanic that lets it chain in team fights. One of the most impactful attackers in the game. | Q12: Paid | R12: legendary_mech
A13: M012 | B13: Eclipse | C13: Legendary | D13: Scout | E13: S | F13: 170,400 | G13: 28 | H13: 24 | I13: 948 | J13: Phase Cloak | K13: Phase Cloak — When active, increases Speed, ignores enemy targeting systems, and cannot be affected by Debuffs. | L13: Ability Cooldown: 10 s | Ability Duration: 8 s | M13: Full debuff immunity; stealth and speed boost; high HP and energy for a scout. | N13: Slightly slower than fastest scouts; no offensive output. | O13: Phase Cloak combines stealth, a speed boost, and complete debuff immunity for 8 seconds. One of the cleanest, most reliable scout abilities — no terrain or collision dependency. High HP and energy for a scout make it a consistent S-tier pick. | P13: 9375 | Q13: A-Coins | R13: legendary_mech
A14: M013 | B14: Gatecrasher | C14: Legendary | D14: Attacker | E14: A | F14: 221,600 | G14: 21 | H14: 32 | I14: 941 | J14: Ion Pod | K14: Ion Pod — Fires a Pod that sticks to surfaces or mechs; releases a damage-over-time beam through surfaces. | L14: Ability Cooldown: 10s | Ion Pod Range: 300m | Ion Beam Duration: 7s | Beam Blast Damage: 60,000 | Ion Beam Damage: 89,900 | Ion Beam Length: 16 m | Mech Blast Damage: 79,900 | Mech Blast Radius: 20 m | M14: Massive damage potential; versatile at long range; punishes enemies behind cover. | N14: Situational, doesn't deal a lot of damage. | O14: Enormous damage ceiling with the Ion Beam on surfaces, but the ability is highly situational — requires the right terrain and positioning to fully exploit | P14: 9375 | Q14: A-Coins | R14: legendary_mech
A15: M014 | B15: Guardian | C15: Rare | D15: Attacker | E15: C | F15: 140,700 | G15: 16 | H15: 32 | I15: 776 | J15: System Crash | K15: System Crash — Disables enemy Weapons and puts their Abilities on cooldown. | L15: Ability Cooldown: 15 s | System Crash Width: 60 m | System Crash Range: 30 m | M15: Shuts down enemy weapons and abilities; high energy capacity. | N15: Very slow; long cooldown. | O15: System Crash completely neutralizes any mech for its duration — no weapons, no abilities. Very slow speed is the main penalty since the ability is close ranged. | P15: 420 | Q15: A-Coins | R15: rare_mech
A16: M015 | B16: Hemlock | C16: Legendary | D16: Support | E16: A | F16: 204,500 | G16: 22 | H16: 24 | I16: 989 | J16: ECM Shot | K16: Pod that dazes enemy for 6s; if enemy takes damage, converts to 2s stun. | L16: Ability Cooldown: 16 s | Missed Ability Cooldown: 3s | Daze Delay: 1.5s | Daze Duration: 6s | EMP Duration: 2s | M16: Can almost permanently stun an enemy with maxed legendary implants. | N16: Very weak when ability is on cooldown. | O16: Good HP, medium energy, medium speed. Strong 1v1 or 2v2 ability at 50% cooldown. | P16: 937500 | Q16: Credits | R16: legendary_mech
A17: M016 | B17: Juggernaut | C17: Uncommon | D17: Tank | E17: C | F17: 152,200 | G17: 16 | H17: 24 | I17: 803 | J17: Personal Shield | K17: Personal Shield — Activates a personal shield that protects the Mech from damage. | L17: Ability Cooldown: 10 s | Ability Duration: 12s | Shield Durability: 31,600 | M17: Reliable damage buffer; decent cooldown. | N17: Slowest tank; lowest HP; no team utility; outclassed at higher rarities. | O17: The simplest tank ability — a plain personal shield with no team utility. Very low HP and the slowest speed of any tank makes it easy to kite. Outclassed by every other tank in the roster. | P17: 45 | Q17: A-Coins | R17: uncommon_mech
A18: M017 | B18: Killshot | C18: Epic B | D18: Scout | E18: B | F18: 119,500 | G18: 29 | H18: 24 | I18: 861 | J18: Melee Dash | K18: Dashes forward and deals impact damage. | L18: Ability Cooldown: 6 s | Ability Damage: 66,900 | Dash Distance: 40 m | Melee Dash Impact Radius: 12 m | M18: Strong melee burst. | N18: Fragile. | O18: A simple dash with no utility beyond the initial impact. Very fragile and the ability offers little beyond a single burst hit. Outclassed by every Legendary scout. | P18: 1865 | Q18: A-Coins | R18: epic_b_mech
A19: M018 | B19: Lacewing | C19: Legendary | D19: Scout | E19: S | F19: 198,900 | G19: 26 | H19: 24 | I19: 982 | J19: Mine Jump | K19: Double jump and places mines at jump location. | L19: Ability Cooldown: 7 s | Jump Distance: 10 m | Mine Damage: 38,000 | Mine Damage Radius: 12 m | Jump Charges: 2 | M19: Reaches high ground easily. | N19: None. | O19: Unique vertical mobility opens angles no other scout can access, and jump-placed mines punish predictable rotations. Niche but rewarding for map-aware players; outperformed by Nomad and Surge in direct combat. | P19: 9375 | Q19: A-Coins | R19: legendary_mech
A20: M019 | B20: Lancer | C20: Common | D20: Scout | E20: C | F20: 85,400 | G20: 25 | H20: 16 | I20: 814 | J20: Jump Jets | K20: Jump Jets — Activates a jump booster to reposition or avoid enemy fire. | L20: Ability Cooldown: 5 s | Jump Distance: 10 m | M20: Fast cooldown; useful for repositioning and high ground. | N20: Purely defensive; low energy cap; outclassed by other scouts. | O20: The simplest scout ability in the game — a repositioning jump with no offensive value. Lowest energy capacity of all scouts and fragile HP make it hard to justify over stronger options. | P20: 400 | Q20: Credits | R20: common_mech
A21: M020 | B21: MD | C21: Uncommon | H21: 16 | P21: 45 | Q21: A-Coins | R21: uncommon_mech
A22: M021 | B22: Mimicker | C22: Legendary | D22: Scout | E22: A | F22: 176,100 | G22: 27 | H22: 32 | I22: 887 | J22: Adaptation | K22: Scans enemy and adapts — Attackers: +50% dmg. Tanks: Gains shield. Scouts: Invisible+faster. Helpers: Heals on kill. | L22: Ability Cooldown: 9 s | Adaptation Range: 100 m | Shield Durability: 89,900 | Mech Healing Speed: 19,980 | Mech Bonus Damage: +30% | Ability Duration (Attacker): 8 s | Ability Duration (Tank): 8 s | Ability Duration (Scout): 8 s | Ability Duration (Support): 5 s | M22: Adaptable to any situation. | N22: Not dominant in any one role. | O22: Unique adaptability makes it versatile in any match, but being mediocre in every role rather than excellent in one holds it back. Best in unpredictable or solo-play scenarios. | P22: 937000 | Q22: Credits | R22: legendary_mech
A23: M022 | B23: Nomad | C23: Legendary | D23: Scout | E23: S | F23: 181,800 | G23: 29 | H23: 24 | I23: 962 | J23: Chain Dash | K23: Dash dealing massive damage + 60% damage reduction. | L23: Ability Cooldown: 8 s | Chain Dash Time: 3 s | Ability Damage: 70,200 | Dash Distance: 45 m | Damage Reduction From Dash: -60% | M23: Fast, agile, durable. | N23: None. | O23: The fastest scout with a dash that deals massive damage while taking only 40% incoming damage. Effectively near-immortal during the ability. The game itself lists no weaknesses — rightfully so. | P23: 9375 | Q23: A-Coins | R23: legendary_mech
A24: M023 | B24: Onyx | C24: Legendary | D24: Attacker | E24: B | F24: 198,900 | G24: 18 | H24: 32 | I24: 914 | J24: Quad Rocket | K24: Fires a rocket which deals light splash damage and heavy damage. | L24: Ability Cooldown: 10s | Damage Per Magazine: 69,833 | Magazine: 4 | Optimal Range: 0-100 m | Projectile Speed: 156 | Damage Radius: 7 m | M24: High burst damage and decent health. | N24: Low speed. | O24: Speed of 18 km/h is the joint slowest among Legendary attackers. The single-target rocket deals decent burst but not enough to compensate for being an easy slow-moving target. | Q24: Paid | R24: legendary_mech
A25: M024 | B25: Orion | C25: Epic B | D25: Support | E25: A | F25: 155,300 | G25: 23 | H25: 24 | I25: 895 | J25: Hunter's Mark | K25: Tracking flare applying Hunter's Mark (+150% dmg from weapons, brief Stasis). Mark spreads to a close enemy when targeted mech dies. | L25: Ability Cooldown: 12 s | Hunters Mark Damage: +150% | Shield Piercing Damage: +88% | Missed Mark Cooldown: 3 s | Mark Transfer Distance: 30 m | Mark Duration: 10 s | Mark Stasis Duration: 3 s | Shield Piercing Ratio: 66% | M25: Almost any weapon becomes strong due to the damage boost. | N25: Very ugly walking style (teammates suffer). | O25: Best Epic mech in the game. Ability makes weak weapons usable. Mid speed, mid energy, slightly low-mid HP. | P25: 1865 | Q25: A-Coins | R25: epic_b_mech
A26: M025 | B26: Outlaw | C26: Legendary | D26: Attacker | E26: S | F26: 213,100 | G26: 20 | H26: 32 | I26: 931 | J26: Foul Play | K26: Pod that reloads/resets a single opponent's mech and weapons. | L26: Ability Cooldown: 15 s | Foul Play Range: 100 m | Foul Play Radius: 5 m | M26: Usually disables an opponent for a short time. | N26: Not effective against short-reload mechs/weapons; useless vs invisible mechs. | O26: Medium speed, good ability, good HP and energy capacity. | P26: 9375 | Q26: A-Coins | R26: legendary_mech
A27: M026 | B27: Panther | C27: Epic C | D27: Attacker | E27: A | F27: 119,500 | G27: 20 | H27: 32 | I27: 793 | J27: Stasis Barrier | K27: Places an immortal Barrier that inflicts Stasis on contact. | L27: Ability Cooldown: 10 s | Ability Duration: 10 s | Stasis Effect Time: 4 s | Stasis Barrier Height: 6 m | M27: Excellent protection and high energy capacity. | N27: Very fragile without the Barrier. | O27: The immortal Barrier with Stasis is powerful zone control, but Panther is very fragile without it. Strong in skilled hands but punished hard on cooldown. | P27: 2425 | Q27: A-Coins | R27: epic_c_mech
A28: M027 | B28: Paragon | C28: Common | D28: Attacker | E28: D | F28: 85,400 | G28: 18 | H28: 32 | I28: 678 | J28: Boost | K28: Makes the mech move faster for a limited amount of time | L28: Ability Cooldown: 9 s | Ability Duration: 6 s | M28: High energy capacity, decent walk speed on ability | N28: Horrible health, low speed when ability is not active | O28: Very low health and speed, paired with a weak ability. The only plus side is the energy capacity and cheapness to upgrade it. | Q28: free | R28: common_mech
A29: M028 | B29: Parasite | C29: Legendary | D29: Tank | E29: S | F29: 261,300 | G29: 20 | H29: 24 | I29: 1,029 | J29: Redirection | K29: Links onto an enemy; takes only 10% damage while transferring 35% to the linked mech. | L29: Ability Cooldown: 11 s | Ability Duration: 12s | Ability Activation Range: 85 m | Redirection Range: 110 m | Damage Received: 10% | Damage Redirected: 35% | M29: Nearly immortal while linked. | N29: Relatively slow. | O29: Huge HP, almost immortal when linked, medium speed. | Q29: Paid | R29: legendary_mech
A30: M029 | B30: Puma | C30: Uncommon | D30: Attacker | E30: D | F30: 67,600 | G30: 20 | H30: 32 | I30: 703 | J30: Shield Wall | K30: Deploys a static Shield Wall that blocks enemy projectiles until it expires or is destroyed. | L30: Ability Cooldown: 10 s | Ability Duration: 10 s | Shield Wall Durability: 67,800 | Shield Wall Height: 6 m | M30: Shield Wall blocks incoming projectiles; decent energy capacity for an Uncommon mech. | N30: Lowest HP of any attacker; static ability is easily avoided by flanking or vertical movement. | O30: One of the original starter mechs. Extremely low HP and power compared to every other attacker. The Shield Wall is defensive but static — easily flanked and outscaled. | P30: 45 | Q30: A-Coins | R30: uncommon_mech
A31: M030 | B31: Redeemer | C31: Epic B | D31: Scout | E31: B | F31: 167,300 | G31: 29 | H31: 24 | I31: 967 | J31: Backtrack | K31: Rewinds 10 seconds and becomes immortal during rewind. | L31: Ability Cooldown: 14 s | Backtrack Timer: 10 | Debuffs Removed: All Debuffs (19) | M31: Extremely agile and fast. | N31: Fragile, long ability cooldown. | O31: Very fast, unique ability. Mid HP, decent energy, high ability cooldown. | P31: 1865 | Q31: A-Coins | R31: epic_b_mech
A32: M031 | B32: Redox | C32: Legendary | D32: Attacker | E32: A | F32: 227,300 | G32: 22 | H32: 32 | I32: 948 | J32: Caustic Blast | K32: Creates a 30m radius caustic blast — stasis + damage over time. Grants a Personal Shield and a Speed Boost for the ability duration. | L32: Ability Cooldown: 8 s | Ability Duration: 6 s | Ability Damage: 79,600 | Caustic Blast Radius: 30 m | Caustic Blast Stasis Time: 6 s | Shield Durability: 31,600 | Speed Boost: +50% | M32: High HP and speed; personal shield extends survivability; 30m AoE stasis slows multiple mechs; strong ability damage; high energy capacity. | N32: Damage over time rather than burst; personal shield is modest; speed boost only active during ability. | O32: Significant buffs bring Redox to Dreadnought-level HP and speed, while adding a personal shield and speed boost during the ability. The 30m AoE stasis+DoT is effective in group fights. Stays out of S because DoT is less impactful than burst damage and the personal shield is modest. | P32: 9375 | Q32: A-Coins | R32: legendary_mech
A33: M032 | B33: Salvor | C33: Legendary | D33: Support | E33: A | F33: 227,300 | G33: 24 | H33: 32 | I33: 948 | J33: Regen Shot | K33: Regen Shot — Fires up to 3 homing healing projectiles at allies. Also heals Salvor. Cannot heal shields or through walls. | L33: Ability Cooldown: 12 s | Regen Shot Range: 100 m | HP Healed (Allies): 60,130 | HP Healed (Self): 30,230 | Regen Shot Charges: 3 | M33: One of two healing mechs; high-burst healing; also heals self; highest power of any support. | N33: Cannot heal shields; requires line of sight. | O33: One of two dedicated healers in the game alongside M.D. Three charges provide up to 180k HP restoration per cycle, with self-healing on top. Significantly outperforms M.D. in burst healing, range (100m vs 10m), and energy capacity. The inability to heal shields or through obstacles is the main limitation. | Q33: Paid | R33: legendary_mech
A34: M033 | B34: Scorpius | C34: Legendary | D34: Attacker | E34: B | F34: 176,100 | G34: 21 | H34: 32 | I34: 887 | J34: Javelin Array | K34: Fires guided shoulder-mounted rockets similar to Javelin racks. | L34: Ability Cooldown: 7 s | Damage Per Magazine: 41,076 | Magazine: 2 | Optimal Range: 16-75 m | Projectile Speed: 20 | Damage Radius: 3 m | Lock Time: 0.7 s | M34: Can hit enemies without direct line of sight; unpredictable. | N34: Mediocre speed, low-damage ability. | O34: Weak ability, good energy capacity, mildly decent HP. | P34: 9375 | Q34: A-Coins | R34: legendary_mech
A35: M034 | B35: Seeker | C35: Legendary | D35: Attacker | E35: S | F35: 193,200 | G35: 22 | H35: 24 | I35: 975 | J35: Warp | K35: Warp — Teleports to an enemy, activates a shield and deals bonus damage on arrival, then returns. | L35: Ability Cooldown: 8 s | Ability Duration: 7 s | Shield Durability: 34,200 | Warp Range: 100 m | Warp Duration: 1s | Warp Bonus Damage: +30% | M35: Invincible during warp; shield and bonus damage on arrival. | N35: Short active window; returns to origin; low energy capacity. | O35: Invincible during warp, shielded on arrival, and boosted damage creates a guaranteed aggressive burst window. Reliable and consistent against campers | P35: 9375 | Q35: A-Coins | R35: legendary_mech
A36: M035 | B36: Sentinel | C36: Epic A | D36: Tank | E36: B | F36: 203,100 | G36: 19 | H36: 24 | I36: 941 | J36: Tall Shield | K36: Tall Shield — Deploys a vertical barrier blocking arcing projectiles. Regenerates faster as Sentinel takes damage at max level. | L36: Ability Cooldown: 12 s | Shield Durability: 57,400 | Ability Cooldown (HP%): 100% - 12s<br>80% - 10s<br>60% - 8s<br>40% - 6s<br>20% - 4s | M36: Blocks arcing projectiles; shield regenerates faster under pressure. | N36: Niche against certain weapons; long cooldown; lower durability than Blockhorn. | O36: Uniquely counters arcing and overhead fire that most shields cannot block. The HP-scaling cooldown reduction makes it more reactive under pressure. Solid HP for an Epic but the niche defensive profile keeps it out of A tier. | P36: 130600 | Q36: Credits | R36: epic_a_mech
A37: M036 | B37: Shadow | C37: Rare | D37: Scout | E37: C | F37: 80,400 | G37: 29 | H37: 16 | I37: 869 | J37: Stealth | K37: Stealth — While active, the Mech moves faster and is ignored by enemy targeting systems. | L37: Ability Cooldown: 8 s | Ability Duration: 12 s | M37: Long stealth duration; speed boost while in stealth. | N37: Low energy capacity; low HP; no offensive bonus. | O37: A long 12s stealth window with a speed boost is genuinely useful for flanking and repositioning. Held back by the lowest energy cap and very low HP. | P37: 420 | Q37: A-Coins | R37: rare_mech
A38: M037 | B38: Silverthorn | C38: Legendary | D38: Attacker | E38: D | F38: 221,600 | G38: 23 | H38: 32 | I38: 941 | J38: Blade Burst | K38: Shoots 5 blades which slow down targets and deal AoE damage. | L38: Ability Cooldown: 7 s | Ability Duration: 3.5 s | Ability Cooldown (Miss): 4 s | Blade Burst DMG Radius: 100 m | Blade Count: 5 | Enemy Speed Reduction: 40 % | Blade Hit Damage: 8,784 | Blade Splash Damage: 2,000 | Extra Damage %: 50% | Maximum Extra Damage: 60,000 | M38: Good control against multiple mechs; fastest attacker in the game. | N38: Low blade damage | O38: Very bad ability, low max damage makes it even worse than mechs like Stalker | P38: 9375 | Q38: A-Coins | R38: legendary_mech
A39: M038 | B39: Slingshot | C39: Uncommon | D39: Scout | E39: C | F39: 67,600 | G39: 29 | H39: 24 | I39: 771 | J39: Force Dash | K39: Force Dash — Launches the Mech forward. Colliding with any object creates an AOE Smash dealing damage to nearby enemies. | L39: Ability Cooldown: 6s | Ability Damage: 22,600 | Dash Distance: 40 m | AOE Smash Impact Radius: 12 m | M39: Maximum speed; AoE dash can hit multiple enemies. | N39: Lowest HP of any scout; ability requires collision to trigger. | O39: The lowest HP of any scout — even below Puma. The Force Dash AoE is fun and can deal decent damage, but Slingshot dies so fast that landing it consistently is very hard. | P39: 45 | Q39: A-Coins | R39: uncommon_mech
A40: M039 | B40: Solis | C40: Legendary | D40: Support | E40: A | F40: 170,400 | G40: 20 | H40: 32 | I40: 880 | J40: Optic Override | K40: Throws 2 orbs that blind enemy mechs in a small radius for 1.5s and grants a +80% Speed Boost for 3s (does NOT work against bots). Cooldown: 12s. | L40: Ability Cooldown: 12 s | Optic Override Radius: 15 m | Blind Effect Duration: 1.5 s | Orb Count: 2 | Speed Boost: +80% | M40: +80% speed boost briefly improves mobility and escape; ability still annoys human opponents. | N40: 1.5s blind is very short; 12s cooldown means long windows of no utility; does not affect bots; below-average base speed. | O40: An effective mech when dealing with other players, also makes ambushes easier. Relatively fragile but has high energy capacity. | P40: 937500 | Q40: Credits | R40: legendary_mech
A41: M040 | B41: Stalker | C41: Rare | D41: Attacker | E41: B | F41: 140,700 | G41: 22 | H41: 24 | I41: 844 | J41: Predator Drive | K41: Predator Drive — Boosts damage dealt and damage taken. Recovers HP per kill while active. | L41: Ability Cooldown: 9 s | Ability Duration: 9 s | Mech Bonus Damage: +50% | Damage Vulnerability: +25% | Heal on Kill: 10% | M41: High burst damage; HP recovery on kill; fast speed. | N41: Increased damage taken while active; low energy capacity. | O41: High risk, high reward. Snowballs well when getting kills but the increased damage taken punishes poor positioning hard. Rewards aggressive, skilled play. | P41: 420 | Q41: A-Coins | R41: rare_mech
A42: M041 | B42: Surge | C42: Legendary | D42: Scout | E42: S | F42: 170,400 | G42: 29 | H42: 24 | I42: 948 | J42: Storm Dash | K42: Dashes and causes a radius inflicting a 3s long stun. | L42: Ability Cooldown: 7 s | abilityDuration: 3 s | Dash Distance: 40 m | EMP Smash: 15 m | M42: Very fast, can stun single or multiple targets. | N42: Not much health; only meant for melee. | O42: Very fast, can stun enemies. Mid HP. | P42: 9375 | Q42: A-Coins | R42: legendary_mech
A43: M042 | B43: Tailsting | C43: Legendary | H43: 24 | Q43: Paid | R43: legendary_mech
A44: M043 | B44: Tengu | C44: Rare | D44: Scout | E44: B | F44: 140,700 | G44: 23 | H44: 16 | I44: 911 | J44: Sky Strike | K44: Sky Strike — Launches into the air with stealth and EMP immunity. On landing, deals heavy AoE damage and applies Stasis in a 15m radius. | L44: Ability Cooldown: 7 s | Ability Damage: 53,600 | Sky Strike Damage Radius: 15 m | Stasis Duration: 5 s | Sky Strike Stasis Radius: 15 m | Stealth Duration: 4 s | M44: Untargetable while airborne; EMP immune in flight; AoE Stasis on landing. | N44: Low energy capacity; slow for a scout; predictable landing arc. | O44: The Sky Strike ability is multi-layered and impressive, but 23 km/h is 6 km/h slower than most scouts — a crippling gap in a role defined by speed. The ability does not cover the window between cooldowns where Tengu is exposed and sluggish. | P44: 420 | Q44: A-Coins | R44: rare_mech
A45: M044 | B45: Volti | C45: Legendary | D45: Attacker | E45: A | F45: 207,400 | G45: 21 | H45: 32 | I45: 924 | J45: Thunderstorm | K45: Drone that hovers over opponent, deals unavoidable damage + electrocution. | L45: Ability Cooldown: 13 s | Ability Duration: 6 s | Thunderstorm DMG Radius: 6 m | Thunderstorm DMG per tick: 10,400 | Thunderstorm Tick Rate: 0.7 | Ability Activation Range: 90 m | Thunderstorm Range: 130 m | M45: Can damage camping enemies all match; high ability damage. | N45: Low ability range. | O45: Decent HP, strong ability vs campers, great energy capacity. | Q45: Paid | R45: legendary_mech
A46: M045 | B46: Vortex | C46: Legendary | D46: Tank | E46: A | F46: 269,900 | G46: 18 | H46: 24 | I46: 1,066 | J46: Nanobot Field | K46: Nanobot Field — Doubles the Mech's Speed and creates a field dealing continuous damage to enemies while reducing damage taken by the Mech and Teammates by 50%. | L46: Ability Cooldown: 13 s | Ability Duration: 8 s | Speed Increase: +100% | Field Damage: 4,700 | Field Radius: 12 m | Field Damage Reduction: -50% | M46: Highest HP in the game; damage reduction for self and teammates; AoE damage; speed doubles during ability. | N46: Slow base speed outside of ability; time-limited. | O46: The Nanobot Field is exceptional — 50% damage reduction for self and teammates plus AoE damage. However, base speed of 18 km/h means Vortex is sluggish between cooldowns and relies entirely on the ability window for mobility. Still very strong, but the base speed penalty is real. | P46: 9375 | Q46: A-Coins | R46: legendary_mech
A47: M046 | B47: Zephyr | C47: Epic B | D47: Support | E47: C | F47: 119,500 | G47: 18 | H47: 24 | I47: 861 | J47: Shock Pulse | K47: Shock Pulse — Stuns mechs for 3 seconds in a 30 meter radius. | L47: Ability Cooldown: 8 s | Ability Duration: 3s | Shock Pulse Radius: 30 m | M47: Large AoE EMP; fast cooldown; disrupts entire pushes. | N47: Very low HP; slow. | O47: The 30m AoE EMP is genuinely powerful for disrupting pushes and protecting teammates. Held back by a short 3s duration, slow 18 km/h speed, and very low HP that makes positioning it safely difficult. | P47: 186600 | Q47: Credits | R47: epic_b_mech

Sheet Mech Upgrade Costs
A1: Rarity Key | B1: Star | C1: Level | D1: Credits | E1: A-Coins | F1: Blueprints | G1: Step
A2: common_mech | B2: 1 | C2: 1 | D2: 75 | E2: 0 | F2: 1 | G2: =(B2-1)*7+C2
A3: uncommon_mech | B3: 1 | C3: 1 | D3: 0 | E3: 0 | F3: 0 | G3: =(B3-1)*7+C3
A4: rare_mech | B4: 1 | C4: 1 | D4: 0 | E4: 0 | F4: 0 | G4: =(B4-1)*7+C4
A5: epic_a_mech | B5: 1 | C5: 1 | D5: 0 | E5: 0 | F5: 0 | G5: =(B5-1)*7+C5
A6: epic_b_mech | B6: 1 | C6: 1 | D6: 0 | E6: 0 | F6: 0 | G6: =(B6-1)*7+C6
A7: epic_c_mech | B7: 1 | C7: 1 | D7: 0 | E7: 0 | F7: 0 | G7: =(B7-1)*7+C7
A8: legendary_mech | B8: 1 | C8: 1 | D8: 825 | E8: 0 | F8: 1 | G8: =(B8-1)*7+C8
A9: common_mech | B9: 1 | C9: 2 | D9: 125 | E9: 0 | F9: 1 | G9: =(B9-1)*7+C9
A10: uncommon_mech | B10: 1 | C10: 2 | D10: 0 | E10: 0 | F10: 0 | G10: =(B10-1)*7+C10
A11: rare_mech | B11: 1 | C11: 2 | D11: 0 | E11: 0 | F11: 0 | G11: =(B11-1)*7+C11
A12: epic_a_mech | B12: 1 | C12: 2 | D12: 0 | E12: 0 | F12: 0 | G12: =(B12-1)*7+C12
A13: epic_b_mech | B13: 1 | C13: 2 | D13: 0 | E13: 0 | F13: 0 | G13: =(B13-1)*7+C13
... A295: legendary_mech | B295: 6 | C295: 7 | D295: 0 | E295: 0 | F295: 0 | G295: =(B295-1)*7+C295

Sheet Weapons
A1: Weapon ID | B1: Name | C1: Base Name | D1: Rarity | E1: Category | F1: Tier | G1: Energy | H1: Fire Rate | I1: Magazine | J1: Reload Speed | K1: Optimal Range | L1: Max Range | M1: Perk | N1: Perk Description | O1: Weapon Effect | P1: Proc Damage | Q1: Proc Interval | R1: Charge Offset | S1: Base DPM | T1: DMG/Energy | U1: Range Rating | V1: Accuracy Rating | W1: Perk Rating | X1: Efficiency Rating | Y1: DMG/Energy Rating | Z1: Strengths | AA1: Weaknesses | AB1: Reasoning | AC1: Unlock Cost | AD1: Unlock Currency | AE1: Rarity Key
A2: W001 | B2: Arc Torrent 6 | C2: Arc Torrent | D2: Epic B | E2: Close Quarters | F2: C | G2: 6 | H2: 124 rpm | I2: 25 | J2: 15s | K2: 0–30m | L2: 30m | M2: High Voltage | N2: Applies a Shock Effect that destabilizes the crosshair of the target. | T2: ~259 | U2: 5 | V2: 3 | W2: 4 | X2: 1 | Y2: 1 | Z2: High Voltage Shock destabilizes aim rapidly. | AA2: Worst dmgPerEnergy of all CQ weapons; one of the worst reloads in the game; raw damage relies entirely on Shock utility. | AB2: CQ utility outlier — Shocks enemies from outside their comfortable fight-back range. One of the worst reloads in the game. Strong in coordinated play; weak solo. | AC2: 77250 | AD2: Credits | AE2: epic_b_weapon_6
A3: W002 | B3: Arc Torrent 10 | C3: Arc Torrent | D3: Epic B | E3: Close Quarters | F3: C | G3: 10 | H3: 124 rpm | I3: 25 | J3: 15s | K3: 0–30m | L3: 30m | M3: High Voltage | N3: Applies a Shock Effect that destabilizes the crosshair of the target. | T3: ~259 | U3: 5 | V3: 3 | W3: 4 | X3: 1 | Y3: 1 | Z3: High Voltage Shock destabilizes aim rapidly. | AA3: Worst dmgPerEnergy of all CQ weapons; one of the worst reloads in the game; raw damage relies entirely on Shock utility. | AB3: CQ utility outlier — Shocks enemies from outside their comfortable fight-back range. One of the worst reloads in the game. Strong in coordinated play; weak solo. | AC3: 870 | AD3: A-Coins | AE3: epic_b_weapon_10
A4: W003 | B4: Arc Torrent 12 | C4: Arc Torrent | D4: Epic B | E4: Close Quarters | F4: C | G4: 12 | H4: 124 rpm | I4: 25 | J4: 15s | K4: 0–30m | L4: 30m | M4: High Voltage | N4: Applies a Shock Effect that destabilizes the crosshair of the target. | T4: ~259 | U4: 5 | V4: 3 | W4: 4 | X4: 1 | Y4: 1 | Z4: High Voltage Shock destabilizes aim rapidly. | AA4: Worst dmgPerEnergy of all CQ weapons; one of the worst reloads in the game; raw damage relies entirely on Shock utility. | AB4: CQ utility outlier — Shocks enemies from outside their comfortable fight-back range. One of the worst reloads in the game. Strong in coordinated play; weak solo. | AC4: 910 | AD4: A-Coins | AE4: epic_b_weapon_12
A5: W004 | B5: Autocannon 2 | C5: Autocannon | D5: Common | E5: Assault | F5: D | G5: 2 | H5: 606 rpm | I5: 90 | J5: 6.6s | K5: 0–45m | L5: 135m | M5: Adaptable | N5: Effective at most ranges and has high ammunition. | T5: 374 | U5: 3 | V5: 4 | W5: 2 | X5: 5 | Y5: 1 | Z5: Extremely energy-efficient; high ammo count; consistent sustained fire at all engagement ranges. | AA5: Low damage ceiling; outscaled quickly by Rare and above; Common rarity limits maximum potential. | AB5: The Autocannon is the reliable starter weapon for tight-energy builds. Adaptable keeps it useful at various ranges but raw damage falls off hard. Worth using as a 2-energy filler — nothing more. | AC5: 50 | AD5: Credits | AE5: common_weapon_2
A6: W005 | B6: Autocannon 4 | C6: Autocannon | D6: Common | E6: Assault | F6: D | G6: 4 | H6: 606 rpm | I6: 90 | J6: 6.6s | K6: 0–45m | L6: 135m | M6: Adaptable | N6: Effective at most ranges and has high ammunition. | T6: 374 | U6: 3 | V6: 4 | W6: 2 | X6: 5 | Y6: 1 | Z6: Extremely energy-efficient; high ammo count; consistent sustained fire at all engagement ranges. | AA6: Low damage ceiling; outscaled quickly by Rare and above; Common rarity limits maximum potential. | AB6: The Autocannon is the reliable starter weapon for tight-energy builds. Adaptable keeps it useful at various ranges but raw damage falls off hard. Worth using as a 2-energy filler — nothing more. | AD6: free | AE6: common_weapon_4
A7: W006 | B7: Berserker 6 | C7: Berserker | D7: Legendary | E7: Assault | F7: B | G7: 6 | H7: 608 rpm | I7: 80 | J7: 8s | K7: 0–60m | L7: 90m | M7: Pulverize | N7: Firing increases bullet dispersion. However, each bullet's Crit Chance steadily increases until the end of the Magazine, up to 100%. | O7: Ramps to 2x crit | T7: ~1,044 | U7: 3 | V7: 2 | W7: 3 | X7: 3 | Y7: 3 | Z7: 100% crit chance at end of magazine is enormous; large 80-round mag gives long crit ramp window; 30% double damage chance stacks on top. | AA7: Bullet dispersion grows as crit chance climbs — late-mag accuracy is poor at range; longest reload of any assault weapon. | AB7: High-risk, high-reward. Crit ramp to 100% is devastating on paper but spread grows simultaneously, undermining accuracy at distance. Best in close-range brawls where spread is irrelevant. The long reload demands you finish fights fast. | AC7: 600000 | AD7: Credits | AE7: legendary_weapon_6
A8: W007 | B8: Berserker 8 | C8: Berserker | D8: Legendary | E8: Assault | F8: B | G8: 8 | H8: 608 rpm | I8: 80 | J8: 8s | K8: 0–60m | L8: 90m | M8: Pulverize | N8: Firing increases bullet dispersion. However, each bullet's Crit Chance steadily increases until the end of the Magazine, up to 100%. | O8: Ramps to 2x crit | T8: ~1,044 | U8: 3 | V8: 2 | W8: 3 | X8: 3 | Y8: 3 | Z8: 100% crit chance at end of magazine is enormous; large 80-round mag gives long crit ramp window; 30% double damage chance stacks on top. | AA8: Bullet dispersion grows as crit chance climbs — late-mag accuracy is poor at range; longest reload of any assault weapon. | AB8: High-risk, high-reward. Crit ramp to 100% is devastating on paper but spread grows simultaneously, undermining accuracy at distance. Best in close-range brawls where spread is irrelevant. The long reload demands you finish fights fast. | AC8: 8275 | AD8: A-Coins | AE8: legendary_weapon_8
A9: W008 | B9: Berserker 10 | C9: Berserker | D9: Legendary | E9: Assault | F9: B | G9: 10 | H9: 608 rpm | I9: 80 | J9: 8s | K9: 0–60m | L9: 90m | M9: Pulverize | N9: Firing increases bullet dispersion. However, each bullet's Crit Chance steadily increases until the end of the Magazine, up to 100%. | O9: Ramps to 2x crit | T9: ~1,044 | U9: 3 | V9: 2 | W9: 3 | X9: 3 | Y9: 3 | Z9: 100% crit chance at end of magazine is enormous; large 80-round mag gives long crit ramp window; 30% double damage chance stacks on top. | AA9: Bullet dispersion grows as crit chance climbs — late-mag accuracy is poor at range; longest reload of any assault weapon. | AB9: High-risk, high-reward. Crit ramp to 100% is devastating on paper but spread grows simultaneously, undermining accuracy at distance. Best in close-range brawls where spread is irrelevant. The long reload demands you finish fights fast. | AC9: 712500 | AD9: Credits | AE9: legendary_weapon_10
A10: W009 | B10: Berserker 12 | C10: Berserker | D10: Legendary | E10: Assault | F10: B | G10: 12 | H10: 608 rpm | I10: 80 | J10: 8s | K10: 0–60m | L10: 90m | M10: Pulverize | N10: Firing increases bullet dispersion. However, each bullet's Crit Chance steadily increases until the end of the Magazine, up to 100%. | O10: Ramps to 2x crit | T10: ~1,044 | U10: 3 | V10: 2 | W10: 3 | X10: 3 | Y10: 3 | Z10: 100% crit chance at end of magazine is enormous; large 80-round mag gives long crit ramp window; 30% double damage chance stacks on top. | AA10: Bullet dispersion grows as crit chance climbs — late-mag accuracy is poor at range; longest reload of any assault weapon. | AB10: High-risk, high-reward. Crit ramp to 100% is devastating on paper but spread grows simultaneously, undermining accuracy at distance. Best in close-range brawls where spread is irrelevant. The long reload demands you finish fights fast. | AC10: 7500 | AD10: A-Coins | AE10: legendary_weapon_12
A11: W010 | B11: Berserker 16 | C11: Berserker | D11: Legendary | E11: Assault | F11: B | G11: 16 | H11: 608 rpm | I11: 80 | J11: 8s | K11: 0–60m | L11: 90m | M11: Pulverize | N11: Firing increases bullet dispersion. However, each bullet's Crit Chance steadily increases until the end of the Magazine, up to 100%. | O11: Ramps to 2x crit | T11: ~1,044 | U11: 3 | V11: 2 | W11: 3 | X11: 3 | Y11: 3 | Z11: 100% crit chance at end of magazine is enormous; large 80-round mag gives long crit ramp window; 30% double damage chance stacks on top. | AA11: Bullet dispersion grows as crit chance climbs — late-mag accuracy is poor at range; longest reload of any assault weapon. | AB11: High-risk, high-reward. Crit ramp to 100% is devastating on paper but spread grows simultaneously, undermining accuracy at distance. Best in close-range brawls where spread is irrelevant. The long reload demands you finish fights fast. | AC11: 827500 | AD11: Credits | AE11: legendary_weapon_16
A12: W011 | B12: Blast RPG 6 | C12: Blast RPG | D12: Legendary | E12: Missile | F12: B | G12: 6 | H12: 170 rpm | I12: 10 | J12: 8s | K12: 0–120m | L12: 120m | M12: Power Play | N12: Missiles deal damage in a large radius around their impact point. Missiles will be attracted towards nearby enemy Mechs on their flight path. | T12: ~692 | U12: 3 | W12: 3 | Y12: 3 | Z12: Large blast radius absorbs near-misses; Power Play auto-attraction reduces aim demand in messy engagements; large 10-shot magazine; 120m range; now competitive DPS/Energy. | AA12: Power Play homing is unreliable against fast or evasive mechs; no CC or utility. | AB12: The damage is quite weak, the homing also makes back hits more difficult, also making the radius less useful. The large blast radius and Power Play attraction remain its identity — the most forgiving Legendary missile now also hits hard enough to matter. | AD12: Paid | AE12: legendary_weapon_6
A13: W012 | B13: Blast RPG 8 | C13: Blast RPG | D13: Legendary | E13: Missile | F13: B | G13: 8 | H13: 170 rpm | I13: 10 | J13: 8s | K13: 0–120m | L13: 120m | M13: Power Play | N13: Missiles deal damage in a large radius around their impact point. Missiles will be attracted towards nearby enemy Mechs on their flight path. | T13: ~692 | U13: 3 | W13: 3 | Y13: 3 | Z13: Large blast radius absorbs near-misses; Power Play auto-attraction reduces aim demand in messy engagements; large 10-shot magazine; 120m range; now competitive DPS/Energy. | AA13: Power Play homing is unreliable against fast or evasive mechs; no CC or utility. | AB13: The damage is quite weak, the homing also makes back hits more difficult, also making the radius less useful. The large blast radius and Power Play attraction remain its identity — the most forgiving Legendary missile now also hits hard enough to matter. | AD13: Paid | AE13: legendary_weapon_8
A14: W013 | B14: Blast RPG 10 | C14: Blast RPG | D14: Legendary | E14: Missile | F14: B | G14: 10 | H14: 170 rpm | I14: 10 | J14: 8s | K14: 0–120m | L14: 120m | M14: Power Play | N14: Missiles deal damage in a large radius around their impact point. Missiles will be attracted towards nearby enemy Mechs on their flight path. | T14: ~692 | U14: 3 | W14: 3 | Y14: 3 | Z14: Large blast radius absorbs near-misses; Power Play auto-attraction reduces aim demand in messy engagements; large 10-shot magazine; 120m range; now competitive DPS/Energy. | AA14: Power Play homing is unreliable against fast or evasive mechs; no CC or utility. | AB14: The damage is quite weak, the homing also makes back hits more difficult, also making the radius less useful. The large blast radius and Power Play attraction remain its identity — the most forgiving Legendary missile now also hits hard enough to matter. | AD14: Paid | AE14: legendary_weapon_10
A15: W014 | B15: Blast RPG 12 | C15: Blast RPG | D15: Legendary | E15: Missile | F15: B | G15: 12 | H15: 170 rpm | I15: 10 | J15: 8s | K15: 0–120m | L15: 120m | M15: Power Play | N15: Missiles deal damage in a large radius around their impact point. Missiles will be attracted towards nearby enemy Mechs on their flight path. | T15: ~692 | U15: 3 | W15: 3 | Y15: 3 | Z15: Large blast radius absorbs near-misses; Power Play auto-attraction reduces aim demand in messy engagements; large 10-shot magazine; 120m range; now competitive DPS/Energy. | AA15: Power Play homing is unreliable against fast or evasive mechs; no CC or utility. | AB15: The damage is quite weak, the homing also makes back hits more difficult, also making the radius less useful. The large blast radius and Power Play attraction remain its identity — the most forgiving Legendary missile now also hits hard enough to matter. | AD15: Paid | AE15: legendary_weapon_12
A16: W015 | B16: Blast RPG 16 | C16: Blast RPG | D16: Legendary | E16: Missile | F16: B | G16: 16 | H16: 170 rpm | I16: 10 | J16: 8s | K16: 0–120m | L16: 120m | M16: Power Play | N16: Missiles deal damage in a large radius around their impact point. Missiles will be attracted towards nearby enemy Mechs on their flight path. | T16: ~692 | U16: 3 | W16: 3 | Y16: 3 | Z16: Large blast radius absorbs near-misses; Power Play auto-attraction reduces aim demand in messy engagements; large 10-shot magazine; 120m range; now competitive DPS/Energy. | AA16: Power Play homing is unreliable against fast or evasive mechs; no CC or utility. | AB16: The damage is quite weak, the homing also makes back hits more difficult, also making the radius less useful. The large blast radius and Power Play attraction remain its identity — the most forgiving Legendary missile now also hits hard enough to matter. | AD16: Paid | AE16: legendary_weapon_16
A17: W016 | B17: Bouncecritter 6 | C17: Bouncecritter | D17: Legendary | G17: 6 | AD17: Paid | AE17: legendary_weapon_6
A18: W017 | B18: Bouncecritter 8 | C18: Bouncecritter | D18: Legendary | G18: 8 | AD18: Paid | AE18: legendary_weapon_8
A19: W018 | B19: Bouncecritter 10 | C19: Bouncecritter | D19: Legendary | G19: 10 | AD19: Paid | AE19: legendary_weapon_10
A20: W019 | B20: Bouncecritter 12 | C20: Bouncecritter | D20: Legendary | G20: 12 | AD20: Paid | AE20: legendary_weapon_12
A21: W020 | B21: Bouncecritter 16 | C21: Bouncecritter | D21: Legendary | G21: 16 | AD21: Paid | AE21: legendary_weapon_16
A22: W021 | B22: Burrow beam 6 | C22: Burrow beam | D22: Legendary | E22: Beam | F22: S | G22: 6 | H22: 154 rpm | I22: 20 | J22: 4.5s | K22: 0–80m | L22: 80m | M22: Piercing Laser | N22: Fires a straight, continuous beam which passes through Mechs. Has a single charge in its Magazine, which reloads when empty. The beam cannot pass through objects, walls or any environmental obstructions. | R22: 1 | T22: ~713 | U22: 3 | W22: 5 | Y22: 3 | Z22: Piercing Laser hits every mech in a line for full damage — real output multiplies in group fights; +6.82% damage per shot partially offsets reload nerf. | AA22: Beam cannot penetrate walls or objects; 80m max range is the second shortest of all Legendary beams; 70% of damage dealt to Shields rather than HP — less effective against shield-depleted targets; longer 13.3s cycle (7.8s fire + 4.5s reload + 1s delay). | AB22: Heavy Damage and a moderate range. Reload is mid but with the correct implant setups its one of the best weapons in the game. | AD22: Paid | AE22: legendary_weapon_6
A23: W022 | B23: Burrow beam 8 | C23: Burrow beam | D23: Legendary | E23: Beam | F23: S | G23: 8 | H23: 154 rpm | I23: 20 | J23: 4.5s | K23: 0–80m | L23: 80m | M23: Piercing Laser | N23: Fires a straight, continuous beam which passes through Mechs. Has a single charge in its Magazine, which reloads when empty. The beam cannot pass through objects, walls or any environmental obstructions. | R23: 1 | T23: ~713 | U23: 3 | W23: 5 | Y23: 3 | Z23: Piercing Laser hits every mech in a line for full damage — real output multiplies in group fights; +6.82% damage per shot partially offsets reload nerf. | AA23: Beam cannot penetrate walls or objects; 80m max range is the second shortest of all Legendary beams; 70% of damage dealt to Shields rather than HP — less effective against shield-depleted targets; longer 13.3s cycle (7.8s fire + 4.5s reload + 1s delay). | AB23: Heavy Damage and a moderate range. Reload is mid but with the correct implant setups its one of the best weapons in the game. | AD23: Paid | AE23: legendary_weapon_8
A24: W023 | B24: Burrow beam 10 | C24: Burrow beam | D24: Legendary | E24: Beam | F24: S | G24: 10 | H24: 154 rpm | I24: 20 | J24: 4.5s | K24: 0–80m | L24: 80m | M24: Piercing Laser | N24: Fires a straight, continuous beam which passes through Mechs. Has a single charge in its Magazine, which reloads when empty. The beam cannot pass through objects, walls or any environmental obstructions. | R24: 1 | T24: ~713 | U24: 3 | W24: 5 | Y24: 3 | Z24: Piercing Laser hits every mech in a line for full damage — real output multiplies in group fights; +6.82% damage per shot partially offsets reload nerf. | AA24: Beam cannot penetrate walls or objects; 80m max range is the second shortest of all Legendary beams; 70% of damage dealt to Shields rather than HP — less effective against shield-depleted targets; longer 13.3s cycle (7.8s fire + 4.5s reload + 1s delay). | AB24: Heavy Damage and a moderate range. Reload is mid but with the correct implant setups its one of the best weapons in the game. | AD24: Paid | AE24: legendary_weapon_10
A25: W024 | B25: Burrow beam 12 | C25: Burrow beam | D25: Legendary | E25: Beam | F25: S | G25: 12 | H25: 154 rpm | I25: 20 | J25: 4.5s | K25: 0–80m | L25: 80m | M25: Piercing Laser | N25: Fires a straight, continuous beam which passes through Mechs. Has a single charge in its Magazine, which reloads when empty. The beam cannot pass through objects, walls or any environmental obstructions. | R25: 1 | T25: ~713 | U25: 3 | W25: 5 | Y25: 3 | Z25: Piercing Laser hits every mech in a line for full damage — real output multiplies in group fights; +6.82% damage per shot partially offsets reload nerf. | AA25: Beam cannot penetrate walls or objects; 80m max range is the second shortest of all Legendary beams; 70% of damage dealt to Shields rather than HP — less effective against shield-depleted targets; longer 13.3s cycle (7.8s fire + 4.5s reload + 1s delay). | AB25: Heavy Damage and a moderate range. Reload is mid but with the correct implant setups its one of the best weapons in the game. | AD25: Paid | AE25: legendary_weapon_12
A26: W025 | B26: Burrow beam 16 | C26: Burrow beam | D26: Legendary | E26: Beam | F26: S | G26: 16 | H26: 154 rpm | I26: 20 | J26: 4.5s | K26: 0–80m | L26: 80m | M26: Piercing Laser | N26: Fires a straight, continuous beam which passes through Mechs. Has a single charge in its Magazine, which reloads when empty. The beam cannot pass through objects, walls or any environmental obstructions. | R26: 1 | T26: ~713 | U26: 3 | W26: 5 | Y26: 3 | Z26: Piercing Laser hits every mech in a line for full damage — real output multiplies in group fights; +6.82% damage per shot partially offsets reload nerf. | AA26: Beam cannot penetrate walls or objects; 80m max range is the second shortest of all Legendary beams; 70% of damage dealt to Shields rather than HP — less effective against shield-depleted targets; longer 13.3s cycle (7.8s fire + 4.5s reload + 1s delay). | AB26: Heavy Damage and a moderate range. Reload is mid but with the correct implant setups its one of the best weapons in the game. | AD26: Paid | AE26: legendary_weapon_16
A27: W026 | B27: Carbine 8 | C27: Carbine | D27: Legendary | E27: Assault | F27: C | G27: 8 | H27: 384 rpm | I27: 50 | J27: 6.2s | K27: 0–30m | L27: 120m | M27: Burst Fire | N27: Fires short bursts of high-damage, high-velocity rounds. | T27: ~636 | U27: 3 | V27: 4 | W27: 3 | X27: 3 | Y27: 2 | Z27: High-velocity projectiles (160 speed); 120m max range offers flexible positioning; burst pattern rewards precise aim. | AA27: Only 30m optimal range — extremely tight engagement window; below-average fire rate; only available at energy 8+. | AB27: The Carbine is a specialist weapon for aggressive mechs that close distance fast. Lacks heavily in damage. | AC27: 8275 | AD27: A-Coins | AE27: legendary_weapon_8
A28: W027 | B28: Carbine 10 | C28: Carbine | D28: Legendary | E28: Assault | F28: C | G28: 10 | H28: 384 rpm | I28: 50 | J28: 6.2s | K28: 0–30m | L28: 120m | M28: Burst Fire | N28: Fires short bursts of high-damage, high-velocity rounds. | T28: ~636 | U28: 3 | V28: 4 | W28: 3 | X28: 3 | Y28: 2 | Z28: High-velocity projectiles (160 speed); 120m max range offers flexible positioning; burst pattern rewards precise aim. | AA28: Only 30m optimal range — extremely tight engagement window; below-average fire rate; only available at energy 8+. | AB28: The Carbine is a specialist weapon for aggressive mechs that close distance fast. Lacks heavily in damage. | AC28: 7125 | AD28: A-Coins | AE28: legendary_weapon_10
A29: W028 | B29: Carbine 12 | C29: Carbine | D29: Legendary | E29: Assault | F29: C | G29: 12 | H29: 384 rpm | I29: 50 | J29: 6.2s | K29: 0–30m | L29: 120m | M29: Burst Fire | N29: Fires short bursts of high-damage, high-velocity rounds. | T29: ~636 | U29: 3 | V29: 4 | W29: 3 | X29: 3 | Y29: 2 | Z29: High-velocity projectiles (160 speed); 120m max range offers flexible positioning; burst pattern rewards precise aim. | AA29: Only 30m optimal range — extremely tight engagement window; below-average fire rate; only available at energy 8+. | AB29: The Carbine is a specialist weapon for aggressive mechs that close distance fast. Lacks heavily in damage. | AC29: 7500 | AD29: A-Coins | AE29: legendary_weapon_12
A30: W029 | B30: Charge Rocket 6 | C30: Charge Rocket | D30: Legendary | E30: Missile | F30: S | G30: 6 | H30: 150 rpm | I30: 5 | J30: 0.4s per rocket | K30: 0–80m | L30: 80m | M30: Whirlwind | N30: Fires 1–5 rockets in quick succession, depending on charge time. Reload Speed is faster if fewer rockets are fired. If 5 rockets are charged, holding the fire button will increase your aim speed. Firing all 5 rockets will grant your Mech a temporary Speed Boost. | O30: Charges over 2s | T30: ~1,353 | U30: 1 | W30: 4 | Y30: 5 | Z30: Highest DPS/Energy in the missile category by a wide margin; Speed Boost on full release enables aggressive kite-in kite-out play; partial charge allows faster reloads when fewer rockets are needed. | AA30: 80m max range — shortest in the entire missile category; requires holding charge to maximise output; loses value if forced into long-range engagements. | AB30: Category benchmark by raw output. Near-instant 5-rocket burst at 150rpm followed by a 2s total reload gives sustained DPS no other missile approaches. The Speed Boost on full release adds mobility that makes the 80m range manageable on fast mechs. S-tier through sheer damage efficiency — the range cap is the only real constraint. | AC30: 600000 | AD30: Credits | AE30: legendary_weapon_6
A31: W030 | B31: Charge Rocket 8 | C31: Charge Rocket | D31: Legendary | E31: Missile | F31: S | G31: 8 | H31: 150 rpm | I31: 5 | J31: 0.4s per rocket | K31: 0–80m | L31: 80m | M31: Whirlwind | N31: Fires 1–5 rockets in quick succession, depending on charge time. Reload Speed is faster if fewer rockets are fired. If 5 rockets are charged, holding the fire button will increase your aim speed. Firing all 5 rockets will grant your Mech a temporary Speed Boost. | O31: Charges over 2s | T31: ~1,353 | U31: 1 | W31: 4 | Y31: 5 | Z31: Highest DPS/Energy in the missile category by a wide margin; Speed Boost on full release enables aggressive kite-in kite-out play; partial charge allows faster reloads when fewer rockets are needed. | AA31: 80m max range — shortest in the entire missile category; requires holding charge to maximise output; loses value if forced into long-range engagements. | AB31: Category benchmark by raw output. Near-instant 5-rocket burst at 150rpm followed by a 2s total reload gives sustained DPS no other missile approaches. The Speed Boost on full release adds mobility that makes the 80m range manageable on fast mechs. S-tier through sheer damage efficiency — the range cap is the only real constraint. | AC31: 7000 | AD31: A-Coins | AE31: legendary_weapon_8
A32: W031 | B32: Charge Rocket 10 | C32: Charge Rocket | D32: Legendary | E32: Missile | F32: S | G32: 10 | H32: 150 rpm | I32: 5 | J32: 0.4s per rocket | K32: 0–80m | L32: 80m | M32: Whirlwind | N32: Fires 1–5 rockets in quick succession, depending on charge time. Reload Speed is faster if fewer rockets are fired. If 5 rockets are charged, holding the fire button will increase your aim speed. Firing all 5 rockets will grant your Mech a temporary Speed Boost. | O32: Charges over 2s | T32: ~1,353 | U32: 1 | W32: 4 | Y32: 5 | Z32: Highest DPS/Energy in the missile category by a wide margin; Speed Boost on full release enables aggressive kite-in kite-out play; partial charge allows faster reloads when fewer rockets are needed. | AA32: 80m max range — shortest in the entire missile category; requires holding charge to maximise output; loses value if forced into long-range engagements. | AB32: Category benchmark by raw output. Near-instant 5-rocket burst at 150rpm followed by a 2s total reload gives sustained DPS no other missile approaches. The Speed Boost on full release adds mobility that makes the 80m range manageable on fast mechs. S-tier through sheer damage efficiency — the range cap is the only real constraint. | AC32: 650000 | AD32: Credits | AE32: legendary_weapon_10
A33: W032 | B33: Charge Rocket 12 | C33: Charge Rocket | D33: Legendary | E33: Missile | F33: S | G33: 12 | H33: 150 rpm | I33: 5 | J33: 0.4s per rocket | K33: 0–80m | L33: 80m | M33: Whirlwind | N33: Fires 1–5 rockets in quick succession, depending on charge time. Reload Speed is faster if fewer rockets are fired. If 5 rockets are charged, holding the fire button will increase your aim speed. Firing all 5 rockets will grant your Mech a temporary Speed Boost. | O33: Charges over 2s | T33: ~1,353 | U33: 1 | W33: 4 | Y33: 5 | Z33: Highest DPS/Energy in the missile category by a wide margin; Speed Boost on full release enables aggressive kite-in kite-out play; partial charge allows faster reloads when fewer rockets are needed. | AA33: 80m max range — shortest in the entire missile category; requires holding charge to maximise output; loses value if forced into long-range engagements. | AB33: Category benchmark by raw output. Near-instant 5-rocket burst at 150rpm followed by a 2s total reload gives sustained DPS no other missile approaches. The Speed Boost on full release adds mobility that makes the 80m range manageable on fast mechs. S-tier through sheer damage efficiency — the range cap is the only real constraint. | AC33: 7500 | AD33: A-Coins | AE33: legendary_weapon_12
A34: W033 | B34: Charge Rocket 16 | C34: Charge Rocket | D34: Legendary | E34: Missile | F34: S | G34: 16 | H34: 150 rpm | I34: 5 | J34: 0.4s per rocket | K34: 0–80m | L34: 80m | M34: Whirlwind | N34: Fires 1–5 rockets in quick succession, depending on charge time. Reload Speed is faster if fewer rockets are fired. If 5 rockets are charged, holding the fire button will increase your aim speed. Firing all 5 rockets will grant your Mech a temporary Speed Boost. | O34: Charges over 2s | T34: ~1,353 | U34: 1 | W34: 4 | Y34: 5 | Z34: Highest DPS/Energy in the missile category by a wide margin; Speed Boost on full release enables aggressive kite-in kite-out play; partial charge allows faster reloads when fewer rockets are needed. | AA34: 80m max range — shortest in the entire missile category; requires holding charge to maximise output; loses value if forced into long-range engagements. | AB34: Category benchmark by raw output. Near-instant 5-rocket burst at 150rpm followed by a 2s total reload gives sustained DPS no other missile approaches. The Speed Boost on full release adds mobility that makes the 80m range manageable on fast mechs. S-tier through sheer damage efficiency — the range cap is the only real constraint. | AC34: 8275 | AD34: A-Coins | AE34: legendary_weapon_16
A35: W034 | B35: Chain Gun 6 | C35: Chain Gun | D35: Legendary | E35: Heavy Duty | F35: A | G35: 6 | H35: 667 rpm | I35: 100 | J35: 9s | K35: 0–75m | L35: 110m | M35: Build Up | N35: This Weapon's Fire Rate increases over time when the trigger is held. | O35: Ramps over 2s / 16 shots | T35: ~1,124 | U35: 3 | V35: 3 | W35: 3 | X35: 4 | Z35: Build Up reaches full fire rate with sustained trigger; large magazine for extended windows; ~25% Double Damage Chance; 110m max range; now competitive per-shot damage. | AA35: Ramp-up punishes short bursts; significant reload; no utility perk unlike Suppressor. | AB35: The +25% damage buff pushes Chain Gun past Dreadshot's per-energy output (~1,119) and into A-tier. Once fully spun up, sustained DPS is among the highest in the heavy category. The ramp-up requirement and lack of utility still keep it behind Suppressor's S-tier Damage Drain, but it is no longer the weakest heavy option. | AC35: 750000 | AD35: Credits | AE35: legendary_weapon_6
A36: W035 | B36: Chain Gun 8 | C36: Chain Gun | D36: Legendary | E36: Heavy Duty | F36: A | G36: 8 | H36: 667 rpm | I36: 100 | J36: 9s | K36: 0–75m | L36: 110m | M36: Build Up | N36: This Weapon's Fire Rate increases over time when the trigger is held. | O36: Ramps over 2s / 16 shots | T36: ~1,124 | U36: 3 | V36: 3 | W36: 3 | X36: 4 | Z36: Build Up reaches full fire rate with sustained trigger; large magazine for extended windows; ~25% Double Damage Chance; 110m max range; now competitive per-shot damage. | AA36: Ramp-up punishes short bursts; significant reload; no utility perk unlike Suppressor. | AB36: The +25% damage buff pushes Chain Gun past Dreadshot's per-energy output (~1,119) and into A-tier. Once fully spun up, sustained DPS is among the highest in the heavy category. The ramp-up requirement and lack of utility still keep it behind Suppressor's S-tier Damage Drain, but it is no longer the weakest heavy option. | AC36: 8275 | AD36: A-Coins | AE36: legendary_weapon_8
A37: W036 | B37: Chain Gun 10 | C37: Chain Gun | D37: Legendary | E37: Heavy Duty | F37: A | G37: 10 | H37: 667 rpm | I37: 100 | J37: 9s | K37: 0–75m | L37: 110m | M37: Build Up | N37: This Weapon's Fire Rate increases over time when the trigger is held. | O37: Ramps over 2s / 16 shots | T37: ~1,124 | U37: 3 | V37: 3 | W37: 3 | X37: 4 | Z37: Build Up reaches full fire rate with sustained trigger; large magazine for extended windows; ~25% Double Damage Chance; 110m max range; now competitive per-shot damage. | AA37: Ramp-up punishes short bursts; significant reload; no utility perk unlike Suppressor. | AB37: The +25% damage buff pushes Chain Gun past Dreadshot's per-energy output (~1,119) and into A-tier. Once fully spun up, sustained DPS is among the highest in the heavy category. The ramp-up requirement and lack of utility still keep it behind Suppressor's S-tier Damage Drain, but it is no longer the weakest heavy option. | AC37: 712500 | AD37: Credits | AE37: legendary_weapon_10
A38: W037 | B38: Chain Gun 12 | C38: Chain Gun | D38: Legendary | E38: Heavy Duty | F38: A | G38: 12 | H38: 667 rpm | I38: 100 | J38: 9s | K38: 0–75m | L38: 110m | M38: Build Up | N38: This Weapon's Fire Rate increases over time when the trigger is held. | O38: Ramps over 2s / 16 shots | T38: ~1,124 | U38: 3 | V38: 3 | W38: 3 | X38: 4 | Z38: Build Up reaches full fire rate with sustained trigger; large magazine for extended windows; ~25% Double Damage Chance; 110m max range; now competitive per-shot damage. | AA38: Ramp-up punishes short bursts; significant reload; no utility perk unlike Suppressor. | AB38: The +25% damage buff pushes Chain Gun past Dreadshot's per-energy output (~1,119) and into A-tier. Once fully spun up, sustained DPS is among the highest in the heavy category. The ramp-up requirement and lack of utility still keep it behind Suppressor's S-tier Damage Drain, but it is no longer the weakest heavy option. | AC38: 7500 | AD38: A-Coins | AE38: legendary_weapon_12
A39: W038 | B39: Chain Gun 16 | C39: Chain Gun | D39: Legendary | E39: Heavy Duty | F39: A | G39: 16 | H39: 667 rpm | I39: 100 | J39: 9s | K39: 0–75m | L39: 110m | M39: Build Up | N39: This Weapon's Fire Rate increases over time when the trigger is held. | O39: Ramps over 2s / 16 shots | T39: ~1,124 | U39: 3 | V39: 3 | W39: 3 | X39: 4 | Z39: Build Up reaches full fire rate with sustained trigger; large magazine for extended windows; ~25% Double Damage Chance; 110m max range; now competitive per-shot damage. | AA39: Ramp-up punishes short bursts; significant reload; no utility perk unlike Suppressor. | AB39: The +25% damage buff pushes Chain Gun past Dreadshot's per-energy output (~1,119) and into A-tier. Once fully spun up, sustained DPS is among the highest in the heavy category. The ramp-up requirement and lack of utility still keep it behind Suppressor's S-tier Damage Drain, but it is no longer the weakest heavy option. | AC39: 8275 | AD39: A-Coins | AE39: legendary_weapon_16
A40: W039 | B40: Continuum 6 | C40: Continuum | D40: Legendary | E40: Sniper | F40: A | G40: 6 | H40: 120 rpm | I40: ∞ | J40: — | K40: 0–140m | L40: 140m | M40: Anti-Matter Mag | N40: Apply constant pressure to your enemies without having to reload. | T40: ~1,765 | U40: 4 | V40: 4 | W40: 5 | X40: 5 | Z40: Infinite magazine — never stops firing; tied with Tetra Rifle for highest DPS/Energy in sniper; 0–140m optimal range; 30% Double Damage Chance. | AA40: No reload rhythm for repositioning breaks; 140m max range shorter than EM Rifle and Railgun; per-shot damage lower than single-shot snipers. | AB40: Category benchmark. Anti-Matter Mag eliminates the reload vulnerability every other sniper shares — the Continuum never creates a zero-output window. Sustains more total damage over any engagement than any other sniper. Undisputed S-tier. | AC40: 600000 | AD40: Credits | AE40: legendary_weapon_6
A41: W040 | B41: Continuum 8 | C41: Continuum | D41: Legendary | E41: Sniper | F41: A | G41: 8 | H41: 120 rpm | I41: ∞ | J41: — | K41: 0–140m | L41: 140m | M41: Anti-Matter Mag | N41: Apply constant pressure to your enemies without having to reload. | T41: ~1,765 | U41: 4 | V41: 4 | W41: 5 | X41: 5 | Z41: Infinite magazine — never stops firing; tied with Tetra Rifle for highest DPS/Energy in sniper; 0–140m optimal range; 30% Double Damage Chance. | AA41: No reload rhythm for repositioning breaks; 140m max range shorter than EM Rifle and Railgun; per-shot damage lower than single-shot snipers. | AB41: Category benchmark. Anti-Matter Mag eliminates the reload vulnerability every other sniper shares — the Continuum never creates a zero-output window. Sustains more total damage over any engagement than any other sniper. Undisputed S-tier. | AC41: 700000 | AD41: Credits | AE41: legendary_weapon_8
A42: W041 | B42: Continuum 10 | C42: Continuum | D42: Legendary | E42: Sniper | F42: A | G42: 10 | H42: 120 rpm | I42: ∞ | J42: — | K42: 0–140m | L42: 140m | M42: Anti-Matter Mag | N42: Apply constant pressure to your enemies without having to reload. | T42: ~1,765 | U42: 4 | V42: 4 | W42: 5 | X42: 5 | Z42: Infinite magazine — never stops firing; tied with Tetra Rifle for highest DPS/Energy in sniper; 0–140m optimal range; 30% Double Damage Chance. | AA42: No reload rhythm for repositioning breaks; 140m max range shorter than EM Rifle and Railgun; per-shot damage lower than single-shot snipers. | AB42: Category benchmark. Anti-Matter Mag eliminates the reload vulnerability every other sniper shares — the Continuum never creates a zero-output window. Sustains more total damage over any engagement than any other sniper. Undisputed S-tier. | AC42: 7000 | AD42: A-Coins | AE42: legendary_weapon_10
A43: W042 | B43: Continuum 12 | C43: Continuum | D43: Legendary | E43: Sniper | F43: A | G43: 12 | H43: 120 rpm | I43: ∞ | J43: — | K43: 0–140m | L43: 140m | M43: Anti-Matter Mag | N43: Apply constant pressure to your enemies without having to reload. | T43: ~1,765 | U43: 4 | V43: 4 | W43: 5 | X43: 5 | Z43: Infinite magazine — never stops firing; tied with Tetra Rifle for highest DPS/Energy in sniper; 0–140m optimal range; 30% Double Damage Chance. | AA43: No reload rhythm for repositioning breaks; 140m max range shorter than EM Rifle and Railgun; per-shot damage lower than single-shot snipers. | AB43: Category benchmark. Anti-Matter Mag eliminates the reload vulnerability every other sniper shares — the Continuum never creates a zero-output window. Sustains more total damage over any engagement than any other sniper. Undisputed S-tier. | AC43: 750000 | AD43: Credits | AE43: legendary_weapon_12
A44: W043 | B44: Continuum 16 | C44: Continuum | D44: Legendary | E44: Sniper | F44: A | G44: 16 | H44: 120 rpm | I44: ∞ | J44: — | K44: 0–140m | L44: 140m | M44: Anti-Matter Mag | N44: Apply constant pressure to your enemies without having to reload. | T44: ~1,765 | U44: 4 | V44: 4 | W44: 5 | X44: 5 | Z44: Infinite magazine — never stops firing; tied with Tetra Rifle for highest DPS/Energy in sniper; 0–140m optimal range; 30% Double Damage Chance. | AA44: No reload rhythm for repositioning breaks; 140m max range shorter than EM Rifle and Railgun; per-shot damage lower than single-shot snipers. | AB44: Category benchmark. Anti-Matter Mag eliminates the reload vulnerability every other sniper shares — the Continuum never creates a zero-output window. Sustains more total damage over any engagement than any other sniper. Undisputed S-tier. | AC44: 8275 | AD44: A-Coins | AE44: legendary_weapon_16
A45: W044 | B45: Compound beam 6 | C45: Compound beam | D45: Legendary | E45: Beam | F45: A | G45: 6 | H45: 157 rpm | I45: 6 | J45: 1.5s | K45: 0–50m | L45: 50m | M45: Energy Charge | N45: Has two firing modes. Deal damage in Beam Mode to apply Stasis to enemies and charge up the Pulse Mode. When ready, Pulse Mode emits a fan-shaped blast that deals increased Damage and applies a short EMP effect. | O45: Pulsed beam 74% | T45: ~1,307 | U45: 2 | W45: 5 | Y45: 5 | Z45: Highest sustained dmgPerEnergy of all beams; tightest cycle in category at 3.8s (2.3s fire + 1.5s reload); beam applies Stasis while charging the EMP fan-blast — dual-status combo is unmatched. | AA45: Shortest range of all Legendary beams at 50m — demands close engagement; dual-mode rhythm requires practice; both effects require landing the correct mode. | AB45: Top sustained efficiency in the beam category. The 3.8s cycle maximises damage uptime and the Stasis-into-EMP combo controls entire groups simultaneously. Short range is the only real constraint — pair with a fast mech to stay inside 50m. | AD45: Paid | AE45: legendary_weapon_6
A46: W045 | B46: Compound beam 8 | C46: Compound beam | D46: Legendary | E46: Beam | F46: A | G46: 8 | H46: 157 rpm | I46: 6 | J46: 1.5s | K46: 0–50m | L46: 50m | M46: Energy Charge | N46: Has two firing modes. Deal damage in Beam Mode to apply Stasis to enemies and charge up the Pulse Mode. When ready, Pulse Mode emits a fan-shaped blast that deals increased Damage and applies a short EMP effect. | O46: Pulsed beam 74% | T46: ~1,307 | U46: 2 | W46: 5 | Y46: 5 | Z46: Highest sustained dmgPerEnergy of all beams; tightest cycle in category at 3.8s (2.3s fire + 1.5s reload); beam applies Stasis while charging the EMP fan-blast — dual-status combo is unmatched. | AA46: Shortest range of all Legendary beams at 50m — demands close engagement; dual-mode rhythm requires practice; both effects require landing the correct mode. | AB46: Top sustained efficiency in the beam category. The 3.8s cycle maximises damage uptime and the Stasis-into-EMP combo controls entire groups simultaneously. Short range is the only real constraint — pair with a fast mech to stay inside 50m. | AD46: Paid | AE46: legendary_weapon_8
A47: W046 | B47: Compound beam 10 | C47: Compound beam | D47: Legendary | E47: Beam | F47: A | G47: 10 | H47: 157 rpm | I47: 6 | J47: 1.5s | K47: 0–50m | L47: 50m | M47: Energy Charge | N47: Has two firing modes. Deal damage in Beam Mode to apply Stasis to enemies and charge up the Pulse Mode. When ready, Pulse Mode emits a fan-shaped blast that deals increased Damage and applies a short EMP effect. | O47: Pulsed beam 74% | T47: ~1,307 | U47: 2 | W47: 5 | Y47: 5 | Z47: Highest sustained dmgPerEnergy of all beams; tightest cycle in category at 3.8s (2.3s fire + 1.5s reload); beam applies Stasis while charging the EMP fan-blast — dual-status combo is unmatched. | AA47: Shortest range of all Legendary beams at 50m — demands close engagement; dual-mode rhythm requires practice; both effects require landing the correct mode. | AB47: Top sustained efficiency in the beam category. The 3.8s cycle maximises damage uptime and the Stasis-into-EMP combo controls entire groups simultaneously. Short range is the only real constraint — pair with a fast mech to stay inside 50m. | AD47: Paid | AE47: legendary_weapon_10
A48: W047 | B48: Compound beam 12 | C48: Compound beam | D48: Legendary | E48: Beam | F48: A | G48: 12 | H48: 157 rpm | I48: 6 | J48: 1.5s | K48: 0–50m | L48: 50m | M48: Energy Charge | N48: Has two firing modes. Deal damage in Beam Mode to apply Stasis to enemies and charge up the Pulse Mode. When ready, Pulse Mode emits a fan-shaped blast that deals increased Damage and applies a short EMP effect. | O48: Pulsed beam 74% | T48: ~1,307 | U48: 2 | W48: 5 | Y48: 5 | Z48: Highest sustained dmgPerEnergy of all beams; tightest cycle in category at 3.8s (2.3s fire + 1.5s reload); beam applies Stasis while charging the EMP fan-blast — dual-status combo is unmatched. | AA48: Shortest range of all Legendary beams at 50m — demands close engagement; dual-mode rhythm requires practice; both effects require landing the correct mode. | AB48: Top sustained efficiency in the beam category. The 3.8s cycle maximises damage uptime and the Stasis-into-EMP combo controls entire groups simultaneously. Short range is the only real constraint — pair with a fast mech to stay inside 50m. | AD48: Paid | AE48: legendary_weapon_12
A49: W048 | B49: Compound beam 16 | C49: Compound beam | D49: Legendary | E49: Beam | F49: A | G49: 16 | H49: 157 rpm | I49: 6 | J49: 1.5s | K49: 0–50m | L49: 50m | M49: Energy Charge | N49: Has two firing modes. Deal damage in Beam Mode to apply Stasis to enemies and charge up the Pulse Mode. When ready, Pulse Mode emits a fan-shaped blast that deals increased Damage and applies a short EMP effect. | O49: Pulsed beam 74% | T49: ~1,307 | U49: 2 | W49: 5 | Y49: 5 | Z49: Highest sustained dmgPerEnergy of all beams; tightest cycle in category at 3.8s (2.3s fire + 1.5s reload); beam applies Stasis while charging the EMP fan-blast — dual-status combo is unmatched. | AA49: Shortest range of all Legendary beams at 50m — demands close engagement; dual-mode rhythm requires practice; both effects require landing the correct mode. | AB49: Top sustained efficiency in the beam category. The 3.8s cycle maximises damage uptime and the Stasis-into-EMP combo controls entire groups simultaneously. Short range is the only real constraint — pair with a fast mech to stay inside 50m. | AD49: Paid | AE49: legendary_weapon_16
A50: W049 | B50: Cryo Javelin 6 | C50: Cryo Javelin | D50: Epic A | E50: Guided | F50: B | G50: 6 | H50: 614 rpm | I50: 6 | J50: 9.7s | K50: 16–75m | L50: 75m | M50: Slowdown | N50: Sustained fire applies a Stasis Effect that dramatically slows the target. | T50: ~453 | U50: 2 | V50: 5 | W50: 4 | X50: 2 | Z50: Stasis through auto-tracking missiles — target cannot sprint away from lock; 6-shot magazine applies Stasis faster than sustained-fire alternatives; 30% Double Damage Chance. | AA50: Only available at energy 6 and 12 — most limited tier selection of any weapon; 75m max range; longest reload in guided. | AB50: Most reliable Stasis delivery in the game — auto-tracking ensures every tick connects regardless of target movement. Two-tier energy limitation is a real constraint, but the CC payoff justifies B-tier in team play. | AD50: Referral | AE50: epic_a_weapon_6
A51: W050 | B51: Cryo Javelin 12 | C51: Cryo Javelin | D51: Epic A | E51: Guided | F51: B | G51: 12 | H51: 614 rpm | I51: 6 | J51: 9.7s | K51: 16–75m | L51: 75m | M51: Slowdown | N51: Sustained fire applies a Stasis Effect that dramatically slows the target. | T51: ~453 | U51: 2 | V51: 5 | W51: 4 | X51: 2 | Z51: Stasis through auto-tracking missiles — target cannot sprint away from lock; 6-shot magazine applies Stasis faster than sustained-fire alternatives; 30% Double Damage Chance. | AA51: Only available at energy 6 and 12 — most limited tier selection of any weapon; 75m max range; longest reload in guided. | AB51: Most reliable Stasis delivery in the game — auto-tracking ensures every tick connects regardless of target movement. Two-tier energy limitation is a real constraint, but the CC payoff justifies B-tier in team play. | AD51: Referral | AE51: epic_a_weapon_12
A52: W051 | B52: Cryo Launcher 6 | C52: Cryo Launcher | D52: Epic A | E52: Barrage | F52: B | G52: 6 | H52: 168 rpm | I52: 9 | J52: 5.5s | K52: 0–95m | L52: 95m | M52: Slowdown | N52: Sustained fire applies a Stasis Effect that dramatically slows the target. | T52: ~693 | U52: 4 | V52: 3 | W52: 4 | X52: 3 | Z52: Stasis locks targets for follow-up rounds, multiplying effective output; second-highest per-shot damage in category; 95m range stays outside most counter-fire. | AA52: Stasis requires sustained fire — fast targets can disengage before it applies; slightly lower output than Nade Launcher at max rank. | AB52: CC anchor of the barrage category. Stasis-locked targets cannot sprint from follow-up rounds, closing the DPS gap with the Nade Launcher through utility. Opens coordinated burst windows no other barrage weapon can create. | AC52: 66550 | AD52: Credits | AE52: epic_a_weapon_6
A53: W052 | B53: Cryo Launcher 8 | C53: Cryo Launcher | D53: Epic A | E53: Barrage | F53: B | G53: 8 | H53: 168 rpm | I53: 9 | J53: 5.5s | K53: 0–95m | L53: 95m | M53: Slowdown | N53: Sustained fire applies a Stasis Effect that dramatically slows the target. | T53: ~693 | U53: 4 | V53: 3 | W53: 4 | X53: 3 | Z53: Stasis locks targets for follow-up rounds, multiplying effective output; second-highest per-shot damage in category; 95m range stays outside most counter-fire. | AA53: Stasis requires sustained fire — fast targets can disengage before it applies; slightly lower output than Nade Launcher at max rank. | AB53: CC anchor of the barrage category. Stasis-locked targets cannot sprint from follow-up rounds, closing the DPS gap with the Nade Launcher through utility. Opens coordinated burst windows no other barrage weapon can create. | AC53: 705 | AD53: A-Coins | AE53: epic_a_weapon_8
A54: W053 | B54: Cryo Launcher 10 | C54: Cryo Launcher | D54: Epic A | E54: Barrage | F54: B | G54: 10 | H54: 168 rpm | I54: 9 | J54: 5.5s | K54: 0–95m | L54: 95m | M54: Slowdown | N54: Sustained fire applies a Stasis Effect that dramatically slows the target. | T54: ~693 | U54: 4 | V54: 3 | W54: 4 | X54: 3 | Z54: Stasis locks targets for follow-up rounds, multiplying effective output; second-highest per-shot damage in category; 95m range stays outside most counter-fire. | AA54: Stasis requires sustained fire — fast targets can disengage before it applies; slightly lower output than Nade Launcher at max rank. | AB54: CC anchor of the barrage category. Stasis-locked targets cannot sprint from follow-up rounds, closing the DPS gap with the Nade Launcher through utility. Opens coordinated burst windows no other barrage weapon can create. | AC54: 73450 | AD54: Credits | AE54: epic_a_weapon_10
A55: W054 | B55: Cryo Launcher 12 | C55: Cryo Launcher | D55: Epic A | E55: Barrage | F55: B | G55: 12 | H55: 168 rpm | I55: 9 | J55: 5.5s | K55: 0–95m | L55: 95m | M55: Slowdown | N55: Sustained fire applies a Stasis Effect that dramatically slows the target. | T55: ~693 | U55: 4 | V55: 3 | W55: 4 | X55: 3 | Z55: Stasis locks targets for follow-up rounds, multiplying effective output; second-highest per-shot damage in category; 95m range stays outside most counter-fire. | AA55: Stasis requires sustained fire — fast targets can disengage before it applies; slightly lower output than Nade Launcher at max rank. | AB55: CC anchor of the barrage category. Stasis-locked targets cannot sprint from follow-up rounds, closing the DPS gap with the Nade Launcher through utility. Opens coordinated burst windows no other barrage weapon can create. | AC55: 760 | AD55: A-Coins | AE55: epic_a_weapon_12
A56: W055 | B56: Cryo Launcher 16 | C56: Cryo Launcher | D56: Epic A | E56: Barrage | F56: B | G56: 16 | H56: 168 rpm | I56: 9 | J56: 5.5s | K56: 0–95m | L56: 95m | M56: Slowdown | N56: Sustained fire applies a Stasis Effect that dramatically slows the target. | T56: ~693 | U56: 4 | V56: 3 | W56: 4 | X56: 3 | Z56: Stasis locks targets for follow-up rounds, multiplying effective output; second-highest per-shot damage in category; 95m range stays outside most counter-fire. | AA56: Stasis requires sustained fire — fast targets can disengage before it applies; slightly lower output than Nade Launcher at max rank. | AB56: CC anchor of the barrage category. Stasis-locked targets cannot sprint from follow-up rounds, closing the DPS gap with the Nade Launcher through utility. Opens coordinated burst windows no other barrage weapon can create. | AC56: 79950 | AD56: Credits | AE56: epic_a_weapon_16
A57: W056 | B57: Disc Launcher 8 | C57: Disc Launcher | D57: Legendary | E57: Guided | F57: B | G57: 8 | H57: 150 rpm | I57: 6 | J57: 6.6s | K57: 0–60m | L57: 120m | M57: Auto-Targeting | N57: Once locked on, this weapon can track and hit the target without manual aiming. | T57: ~713 | U57: 2 | V57: 5 | W57: 3 | X57: 4 | Z57: Highest per-shot damage in guided; by far the widest blast radius in category — near-misses irrelevant; auto-tracking guarantees hits; now comparable DPS/Energy to Strike Rocket. | AA57: 60m optimal range — shortest of all Legendary guided; only at energy 8/12/16; Auto-Targeting perk is same as Rare Javelin Rack — no added mechanic. | AB57: Its near impossible to deal back damage at close range. At ~713 DPS/Energy it now matches Strike Rocket and the near-10m blast radius combined with auto-tracking makes it arguably the easiest guided weapon to connect reliably. Still limited to 60m optimal range but the damage payoff within that window is decent. | AC57: 826750 | AD57: Credits | AE57: legendary_weapon_8
A58: W057 | B58: Disc Launcher 12 | C58: Disc Launcher | D58: Legendary | E58: Guided | F58: B | G58: 12 | H58: 150 rpm | I58: 6 | J58: 6.6s | K58: 0–60m | L58: 120m | M58: Auto-Targeting | N58: Once locked on, this weapon can track and hit the target without manual aiming. | T58: ~713 | U58: 2 | V58: 5 | W58: 3 | X58: 4 | Z58: Highest per-shot damage in guided; by far the widest blast radius in category — near-misses irrelevant; auto-tracking guarantees hits; now comparable DPS/Energy to Strike Rocket. | AA58: 60m optimal range — shortest of all Legendary guided; only at energy 8/12/16; Auto-Targeting perk is same as Rare Javelin Rack — no added mechanic. | AB58: Its near impossible to deal back damage at close range. At ~713 DPS/Energy it now matches Strike Rocket and the near-10m blast radius combined with auto-tracking makes it arguably the easiest guided weapon to connect reliably. Still limited to 60m optimal range but the damage payoff within that window is decent. | AC58: 7500 | AD58: A-Coins | AE58: legendary_weapon_12
A59: W058 | B59: Disc Launcher 16 | C59: Disc Launcher | D59: Legendary | E59: Guided | F59: B | G59: 16 | H59: 150 rpm | I59: 6 | J59: 6.6s | K59: 0–60m | L59: 120m | M59: Auto-Targeting | N59: Once locked on, this weapon can track and hit the target without manual aiming. | T59: ~713 | U59: 2 | V59: 5 | W59: 3 | X59: 4 | Z59: Highest per-shot damage in guided; by far the widest blast radius in category — near-misses irrelevant; auto-tracking guarantees hits; now comparable DPS/Energy to Strike Rocket. | AA59: 60m optimal range — shortest of all Legendary guided; only at energy 8/12/16; Auto-Targeting perk is same as Rare Javelin Rack — no added mechanic. | AB59: Its near impossible to deal back damage at close range. At ~713 DPS/Energy it now matches Strike Rocket and the near-10m blast radius combined with auto-tracking makes it arguably the easiest guided weapon to connect reliably. Still limited to 60m optimal range but the damage payoff within that window is decent. | AC59: 8275 | AD59: A-Coins | AE59: legendary_weapon_16
A60: W059 | B60: Disruptor 6 | C60: Disruptor | D60: Legendary | E60: Missile | F60: A | G60: 6 | H60: 10 rpm | I60: 1 | J60: 5.5s | K60: 0–91m | L60: 91m | M60: Devastation | N60: Each shot deals Path Damage during flight and Splash Damage on impact. | T60: ~147 | U60: 2 | W60: 3 | Y60: 1 | Z60: Devastation deals damage along the entire flight path — hits grouped enemies multiple times; 7m path radius and 7m splash radius punish packed formations; 0.3s path damage timer adds lingering area. | AA60: Lowest DPS/Energy of any Legendary missile; single-shot magazine demands a reload every 5.5s; path damage only relevant against stationary or grouped targets. | AB60: Niche formation punisher. Devastation is uniquely powerful when the flight path intersects multiple clustered enemies — path damage effectively multiplies per-shot value. Against isolated mobile targets, however, it is simply the lowest-DPS Legendary missile with a punishing single-shot reload rhythm. | AC60: 755000 | AD60: Credits | AE60: legendary_weapon_6
A61: W060 | B61: Disruptor 8 | C61: Disruptor | D61: Legendary | E61: Missile | F61: A | G61: 8 | H61: 10 rpm | I61: 1 | J61: 5.5s | K61: 0–91m | L61: 91m | M61: Devastation | N61: Each shot deals Path Damage during flight and Splash Damage on impact. | T61: ~147 | U61: 2 | W61: 3 | Y61: 1 | Z61: Devastation deals damage along the entire flight path — hits grouped enemies multiple times; 7m path radius and 7m splash radius punish packed formations; 0.3s path damage timer adds lingering area. | AA61: Lowest DPS/Energy of any Legendary missile; single-shot magazine demands a reload every 5.5s; path damage only relevant against stationary or grouped targets. | AB61: Niche formation punisher. Devastation is uniquely powerful when the flight path intersects multiple clustered enemies — path damage effectively multiplies per-shot value. Against isolated mobile targets, however, it is simply the lowest-DPS Legendary missile with a punishing single-shot reload rhythm. | AC61: 8275 | AD61: A-Coins | AE61: legendary_weapon_8
A62: W061 | B62: Disruptor 10 | C62: Disruptor | D62: Legendary | E62: Missile | F62: A | G62: 10 | H62: 10 rpm | I62: 1 | J62: 5.5s | K62: 0–91m | L62: 91m | M62: Devastation | N62: Each shot deals Path Damage during flight and Splash Damage on impact. | T62: ~147 | U62: 2 | W62: 3 | Y62: 1 | Z62: Devastation deals damage along the entire flight path — hits grouped enemies multiple times; 7m path radius and 7m splash radius punish packed formations; 0.3s path damage timer adds lingering area. | AA62: Lowest DPS/Energy of any Legendary missile; single-shot magazine demands a reload every 5.5s; path damage only relevant against stationary or grouped targets. | AB62: Niche formation punisher. Devastation is uniquely powerful when the flight path intersects multiple clustered enemies — path damage effectively multiplies per-shot value. Against isolated mobile targets, however, it is simply the lowest-DPS Legendary missile with a punishing single-shot reload rhythm. | AC62: 7125 | AD62: A-Coins | AE62: legendary_weapon_10
A63: W062 | B63: Disruptor 12 | C63: Disruptor | D63: Legendary | E63: Missile | F63: A | G63: 12 | H63: 10 rpm | I63: 1 | J63: 5.5s | K63: 0–91m | L63: 91m | M63: Devastation | N63: Each shot deals Path Damage during flight and Splash Damage on impact. | T63: ~147 | U63: 2 | W63: 3 | Y63: 1 | Z63: Devastation deals damage along the entire flight path — hits grouped enemies multiple times; 7m path radius and 7m splash radius punish packed formations; 0.3s path damage timer adds lingering area. | AA63: Lowest DPS/Energy of any Legendary missile; single-shot magazine demands a reload every 5.5s; path damage only relevant against stationary or grouped targets. | AB63: Niche formation punisher. Devastation is uniquely powerful when the flight path intersects multiple clustered enemies — path damage effectively multiplies per-shot value. Against isolated mobile targets, however, it is simply the lowest-DPS Legendary missile with a punishing single-shot reload rhythm. | AC63: 755000 | AD63: Credits | AE63: legendary_weapon_12
A64: W063 | B64: Disruptor 16 | C64: Disruptor | D64: Legendary | E64: Missile | F64: A | G64: 16 | H64: 10 rpm | I64: 1 | J64: 5.5s | K64: 0–91m | L64: 91m | M64: Devastation | N64: Each shot deals Path Damage during flight and Splash Damage on impact. | T64: ~147 | U64: 2 | W64: 3 | Y64: 1 | Z64: Devastation deals damage along the entire flight path — hits grouped enemies multiple times; 7m path radius and 7m splash radius punish packed formations; 0.3s path damage timer adds lingering area. | AA64: Lowest DPS/Energy of any Legendary missile; single-shot magazine demands a reload every 5.5s; path damage only relevant against stationary or grouped targets. | AB64: Niche formation punisher. Devastation is uniquely powerful when the flight path intersects multiple clustered enemies — path damage effectively multiplies per-shot value. Against isolated mobile targets, however, it is simply the lowest-DPS Legendary missile with a punishing single-shot reload rhythm. | AC64: 826750 | AD64: Credits | AE64: legendary_weapon_16
A65: W064 | B65: Dreadshot 6 | C65: Dreadshot | D65: Legendary | E65: Heavy Duty | F65: B | G65: 6 | H65: 93 rpm | I65: 15 | J65: 7s | K65: 0–100m | L65: 120m | M65: Heavy Hitter | N65: Each shot deals a massive amount of Damage to the target. | T65: ~1,119 | U65: 4 | V65: 4 | W65: 4 | X65: 4 | Z65: Highest damage per shot in heavy duty; longest range in class; high accuracy and fast projectile speed; ~25% Double Damage Chance. | AA65: Slowest fire rate in category — each miss is costly; lower DPM than Minigun and Hellfire within their optimal conditions. | AB65: All-range precision weapon. Heavy Hitter delivers the biggest individual shots in class from the longest range — punishing enemies from positions the Hellfire and Chain Gun cannot reach. Slow fire rate demands aim discipline, but per-shot payoff justifies A-tier. | AC65: 700000 | AD65: Credits | AE65: legendary_weapon_6
A66: W065 | B66: Dreadshot 8 | C66: Dreadshot | D66: Legendary | E66: Heavy Duty | F66: B | G66: 8 | H66: 93 rpm | I66: 15 | J66: 7s | K66: 0–100m | L66: 120m | M66: Heavy Hitter | N66: Each shot deals a massive amount of Damage to the target. | T66: ~1,119 | U66: 4 | V66: 4 | W66: 4 | X66: 4 | Z66: Highest damage per shot in heavy duty; longest range in class; high accuracy and fast projectile speed; ~25% Double Damage Chance. | AA66: Slowest fire rate in category — each miss is costly; lower DPM than Minigun and Hellfire within their optimal conditions. | AB66: All-range precision weapon. Heavy Hitter delivers the biggest individual shots in class from the longest range — punishing enemies from positions the Hellfire and Chain Gun cannot reach. Slow fire rate demands aim discipline, but per-shot payoff justifies A-tier. | AC66: 800000 | AD66: Credits | AE66: legendary_weapon_8
A67: W066 | B67: Dreadshot 10 | C67: Dreadshot | D67: Legendary | E67: Heavy Duty | F67: B | G67: 8 | H67: 93 rpm | I67: 15 | J67: 7s | K67: 0–100m | L67: 120m | M67: Heavy Hitter | N67: Each shot deals a massive amount of Damage to the target. | T67: ~1,119 | U67: 4 | V67: 4 | W67: 4 | X67: 4 | Z67: Highest damage per shot in heavy duty; longest range in class; high accuracy and fast projectile speed; ~25% Double Damage Chance. | AA67: Slowest fire rate in category — each miss is costly; lower DPM than Minigun and Hellfire within their optimal conditions. | AB67: All-range precision weapon. Heavy Hitter delivers the biggest individual shots in class from the longest range — punishing enemies from positions the Hellfire and Chain Gun cannot reach. Slow fire rate demands aim discipline, but per-shot payoff justifies A-tier. | AC67: 700000 | AD67: Credits | AE67: legendary_weapon_8
A68: W067 | B68: Dreadshot 12 | C68: Dreadshot | D68: Legendary | E68: Heavy Duty | F68: B | G68: 12 | H68: 93 rpm | I68: 15 | J68: 7s | K68: 0–100m | L68: 120m | M68: Heavy Hitter | N68: Each shot deals a massive amount of Damage to the target. | T68: ~1,119 | U68: 4 | V68: 4 | W68: 4 | X68: 4 | Z68: Highest damage per shot in heavy duty; longest range in class; high accuracy and fast projectile speed; ~25% Double Damage Chance. | AA68: Slowest fire rate in category — each miss is costly; lower DPM than Minigun and Hellfire within their optimal conditions. | AB68: All-range precision weapon. Heavy Hitter delivers the biggest individual shots in class from the longest range — punishing enemies from positions the Hellfire and Chain Gun cannot reach. Slow fire rate demands aim discipline, but per-shot payoff justifies A-tier. | AC68: 7500 | AD68: A-Coins | AE68: legendary_weapon_12
A69: W068 | B69: Dreadshot 16 | C69: Dreadshot | D69: Legendary | E69: Heavy Duty | F69: B | G69: 16 | H69: 93 rpm | I69: 15 | J69: 7s | K69: 0–100m | L69: 120m | M69: Heavy Hitter | N69: Each shot deals a massive amount of Damage to the target. | T69: ~1,119 | U69: 4 | V69: 4 | W69: 4 | X69: 4 | Z69: Highest damage per shot in heavy duty; longest range in class; high accuracy and fast projectile speed; ~25% Double Damage Chance. | AA69: Slowest fire rate in category — each miss is costly; lower DPM than Minigun and Hellfire within their optimal conditions. | AB69: All-range precision weapon. Heavy Hitter delivers the biggest individual shots in class from the longest range — punishing enemies from positions the Hellfire and Chain Gun cannot reach. Slow fire rate demands aim discipline, but per-shot payoff justifies A-tier. | AC69: 8275 | AD69: A-Coins | AE69: legendary_weapon_16
A70: W069 | B70: EM Rifle 6 | C70: EM Rifle | D70: Legendary | E70: Sniper | F70: C | G70: 6 | H70: 10 rpm | I70: 1 | J70: 5.3s | K70: 75m+ | L70: 165m | M70: Power Shot | N70: This weapon is capable of Double Damage shots. | R70: 0.7 | T70: ~516 | U70: 3 | V70: 3 | W70: 4 | X70: 3 | Z70: Highest single-shot damage in sniper; 40% Double Damage Chance; hitscan-level projectile speed. | AA70: Single-shot magazine — every miss is catastrophic; brief shot delay telegraphs the shot; minimum range dead zone against close attackers. | AB70: Highest-skill sniper. A well-placed shot can deal enormous damage, especially when paired with orion; a double-proc can two-shot nearly anything. Nearly impossible to dodge once fired, but the brief shot delay and single-shot reload punish every miss ruthlessly. Also struggles a lot against mods | AC70: 7500 | AD70: A-Coins | AE70: legendary_weapon_6
A71: W070 | B71: EM Rifle 8 | C71: EM Rifle | D71: Legendary | E71: Sniper | F71: C | G71: 8 | H71: 10 rpm | I71: 1 | J71: 5.3s | K71: 75m+ | L71: 165m | M71: Power Shot | N71: This weapon is capable of Double Damage shots. | R71: 0.7 | T71: ~516 | U71: 3 | V71: 3 | W71: 4 | X71: 3 | Z71: Highest single-shot damage in sniper; 40% Double Damage Chance; hitscan-level projectile speed. | AA71: Single-shot magazine — every miss is catastrophic; brief shot delay telegraphs the shot; minimum range dead zone against close attackers. | AB71: Highest-skill sniper. A well-placed shot can deal enormous damage, especially when paired with orion; a double-proc can two-shot nearly anything. Nearly impossible to dodge once fired, but the brief shot delay and single-shot reload punish every miss ruthlessly. Also struggles a lot against mods | AC71: 8275 | AD71: A-Coins | AE71: legendary_weapon_8
A72: W071 | B72: EM Rifle 10 | C72: EM Rifle | D72: Legendary | E72: Sniper | F72: C | G72: 10 | H72: 10 rpm | I72: 1 | J72: 5.3s | K72: 75m+ | L72: 165m | M72: Power Shot | N72: This weapon is capable of Double Damage shots. | R72: 0.7 | T72: ~516 | U72: 3 | V72: 3 | W72: 4 | X72: 3 | Z72: Highest single-shot damage in sniper; 40% Double Damage Chance; hitscan-level projectile speed. | AA72: Single-shot magazine — every miss is catastrophic; brief shot delay telegraphs the shot; minimum range dead zone against close attackers. | AB72: Highest-skill sniper. A well-placed shot can deal enormous damage, especially when paired with orion; a double-proc can two-shot nearly anything. Nearly impossible to dodge once fired, but the brief shot delay and single-shot reload punish every miss ruthlessly. Also struggles a lot against mods | AC72: 7125 | AD72: A-Coins | AE72: legendary_weapon_10
A73: W072 | B73: EM Rifle 12 | C73: EM Rifle | D73: Legendary | E73: Sniper | F73: C | G73: 12 | H73: 10 rpm | I73: 1 | J73: 5.3s | K73: 75m+ | L73: 165m | M73: Power Shot | N73: This weapon is capable of Double Damage shots. | R73: 0.7 | T73: ~516 | U73: 3 | V73: 3 | W73: 4 | X73: 3 | Z73: Highest single-shot damage in sniper; 40% Double Damage Chance; hitscan-level projectile speed. | AA73: Single-shot magazine — every miss is catastrophic; brief shot delay telegraphs the shot; minimum range dead zone against close attackers. | AB73: Highest-skill sniper. A well-placed shot can deal enormous damage, especially when paired with orion; a double-proc can two-shot nearly anything. Nearly impossible to dodge once fired, but the brief shot delay and single-shot reload punish every miss ruthlessly. Also struggles a lot against mods | AC73: 7500 | AD73: A-Coins | AE73: legendary_weapon_12
A74: W073 | B74: EM Rifle 16 | C74: EM Rifle | D74: Legendary | E74: Sniper | F74: C | G74: 16 | H74: 10 rpm | I74: 1 | J74: 5.3s | K74: 75m+ | L74: 165m | M74: Power Shot | N74: This weapon is capable of Double Damage shots. | R74: 0.7 | T74: ~516 | U74: 3 | V74: 3 | W74: 4 | X74: 3 | Z74: Highest single-shot damage in sniper; 40% Double Damage Chance; hitscan-level projectile speed. | AA74: Single-shot magazine — every miss is catastrophic; brief shot delay telegraphs the shot; minimum range dead zone against close attackers. | AB74: Highest-skill sniper. A well-placed shot can deal enormous damage, especially when paired with orion; a double-proc can two-shot nearly anything. Nearly impossible to dodge once fired, but the brief shot delay and single-shot reload punish every miss ruthlessly. Also struggles a lot against mods | AC74: 8275 | AD74: A-Coins | AE74: legendary_weapon_16
A75: W074 | B75: Ember Gun 6 | C75: Ember Gun | D75: Epic C | E75: Close Quarters | F75: A | G75: 6 | H75: 412 rpm | I75: 2 | J75: 1.5s | K75: 0–20m | L75: 30m | M75: Twin Shots | N75: Fires twice, applying Weaken. Fast reload for a brutal follow-up. | O75: Weakens from shot 2, +50% dmg | T75: ~1,265 | U75: 4 | V75: 3 | W75: 3 | X75: 4 | Y75: 4 | Z75: Weaken on both shots boosts allied damage; fast reload creates near-constant burst cycling; strong DPS at max rank. | AA75: Tiny 2-shot magazine punishes every miss; hit cone narrows sharply at max rank; contributes more in team play than solo. | AB75: Team-oriented burst weapon. Twin Shots applies Weaken on both hits for allied follow-up damage. Fast reload stays aggressive but the tiny magazine is punishing solo — punches above its numbers in coordinated play, falls short of Howler and Repeater in isolation. | AC75: 87900 | AD75: Credits | AE75: epic_c_weapon_6
A76: W075 | B76: Ember Gun 8 | C76: Ember Gun | D76: Epic C | E76: Close Quarters | F76: A | G76: 8 | H76: 412 rpm | I76: 2 | J76: 1.5s | K76: 0–20m | L76: 30m | M76: Twin Shots | N76: Fires twice, applying Weaken. Fast reload for a brutal follow-up. | O76: Weakens from shot 2, +50% dmg | T76: ~1,265 | U76: 4 | V76: 3 | W76: 3 | X76: 4 | Y76: 4 | Z76: Weaken on both shots boosts allied damage; fast reload creates near-constant burst cycling; strong DPS at max rank. | AA76: Tiny 2-shot magazine punishes every miss; hit cone narrows sharply at max rank; contributes more in team play than solo. | AB76: Team-oriented burst weapon. Twin Shots applies Weaken on both hits for allied follow-up damage. Fast reload stays aggressive but the tiny magazine is punishing solo — punches above its numbers in coordinated play, falls short of Howler and Repeater in isolation. | AC76: 95000 | AD76: Credits | AE76: epic_c_weapon_8
A77: W076 | B77: Ember Gun 10 | C77: Ember Gun | D77: Epic C | E77: Close Quarters | F77: A | G77: 10 | H77: 412 rpm | I77: 2 | J77: 1.5s | K77: 0–20m | L77: 30m | M77: Twin Shots | N77: Fires twice, applying Weaken. Fast reload for a brutal follow-up. | O77: Weakens from shot 2, +50% dmg | T77: ~1,265 | U77: 4 | V77: 3 | W77: 3 | X77: 4 | Y77: 4 | Z77: Weaken on both shots boosts allied damage; fast reload creates near-constant burst cycling; strong DPS at max rank. | AA77: Tiny 2-shot magazine punishes every miss; hit cone narrows sharply at max rank; contributes more in team play than solo. | AB77: Team-oriented burst weapon. Twin Shots applies Weaken on both hits for allied follow-up damage. Fast reload stays aggressive but the tiny magazine is punishing solo — punches above its numbers in coordinated play, falls short of Howler and Repeater in isolation. | AC77: 1005 | AD77: A-Coins | AE77: epic_c_weapon_10
A78: W077 | B78: Ember Gun 12 | C78: Ember Gun | D78: Epic C | E78: Close Quarters | F78: A | G78: 12 | H78: 412 rpm | I78: 2 | J78: 1.5s | K78: 0–20m | L78: 30m | M78: Twin Shots | N78: Fires twice, applying Weaken. Fast reload for a brutal follow-up. | O78: Weakens from shot 2, +50% dmg | T78: ~1,265 | U78: 4 | V78: 3 | W78: 3 | X78: 4 | Y78: 4 | Z78: Weaken on both shots boosts allied damage; fast reload creates near-constant burst cycling; strong DPS at max rank. | AA78: Tiny 2-shot magazine punishes every miss; hit cone narrows sharply at max rank; contributes more in team play than solo. | AB78: Team-oriented burst weapon. Twin Shots applies Weaken on both hits for allied follow-up damage. Fast reload stays aggressive but the tiny magazine is punishing solo — punches above its numbers in coordinated play, falls short of Howler and Repeater in isolation. | AC78: 1055 | AD78: A-Coins | AE78: epic_c_weapon_12
A79: W078 | B79: Ember Gun 16 | C79: Ember Gun | D79: Epic C | E79: Close Quarters | F79: A | G79: 16 | H79: 412 rpm | I79: 2 | J79: 1.5s | K79: 0–20m | L79: 30m | M79: Twin Shots | N79: Fires twice, applying Weaken. Fast reload for a brutal follow-up. | O79: Weakens from shot 2, +50% dmg | T79: ~1,265 | U79: 4 | V79: 3 | W79: 3 | X79: 4 | Y79: 4 | Z79: Weaken on both shots boosts allied damage; fast reload creates near-constant burst cycling; strong DPS at max rank. | AA79: Tiny 2-shot magazine punishes every miss; hit cone narrows sharply at max rank; contributes more in team play than solo. | AB79: Team-oriented burst weapon. Twin Shots applies Weaken on both hits for allied follow-up damage. Fast reload stays aggressive but the tiny magazine is punishing solo — punches above its numbers in coordinated play, falls short of Howler and Repeater in isolation. | AC79: 1130 | AD79: A-Coins | AE79: epic_c_weapon_16
A80: W079 | B80: Fragment Gun 6 | C80: Fragment Gun | D80: Rare | E80: Close Quarters | F80: B | G80: 6 | H80: 90 rpm | I80: 6 | J80: 6s | K80: 0–13m | L80: 32m | M80: Wide Hit Cone | N80: Shots fire in a cone, making them good at hitting fast targets or at short range. | T80: ~1,052 | U80: 1 | V80: 3 | W80: 2 | X80: 3 | Y80: 3 | Z80: Highest damage per shot of any Rare CQ weapon; wide hit cone connects reliably against mobile targets; available across five energy tiers. | AA80: 13m optimal range demands near point-blank positioning; punishes every miss; small magazine. | AB80: Dependable Rare with serious per-shot damage. The 13m optimal range is the defining constraint — demands extreme aggression. Outperformed by all Epic/Legendary CQ options but solid when energy budget is tight. | AC80: 21850 | AD80: Credits | AE80: rare_weapon_6
A81: W080 | B81: Fragment Gun 8 | C81: Fragment Gun | D81: Rare | E81: Close Quarters | F81: B | G81: 8 | H81: 90 rpm | I81: 6 | J81: 6s | K81: 0–13m | L81: 32m | M81: Wide Hit Cone | N81: Shots fire in a cone, making them good at hitting fast targets or at short range. | T81: ~1,052 | U81: 1 | V81: 3 | W81: 2 | X81: 3 | Y81: 3 | Z81: Highest damage per shot of any Rare CQ weapon; wide hit cone connects reliably against mobile targets; available across five energy tiers. | AA81: 13m optimal range demands near point-blank positioning; punishes every miss; small magazine. | AB81: Dependable Rare with serious per-shot damage. The 13m optimal range is the defining constraint — demands extreme aggression. Outperformed by all Epic/Legendary CQ options but solid when energy budget is tight. | AC81: 22850 | AD81: Credits | AE81: rare_weapon_8
A82: W081 | B82: Fragment Gun 10 | C82: Fragment Gun | D82: Rare | E82: Close Quarters | F82: B | G82: 10 | H82: 90 rpm | I82: 6 | J82: 6s | K82: 0–13m | L82: 32m | M82: Wide Hit Cone | N82: Shots fire in a cone, making them good at hitting fast targets or at short range. | T82: ~1,052 | U82: 1 | V82: 3 | W82: 2 | X82: 3 | Y82: 3 | Z82: Highest damage per shot of any Rare CQ weapon; wide hit cone connects reliably against mobile targets; available across five energy tiers. | AA82: 13m optimal range demands near point-blank positioning; punishes every miss; small magazine. | AB82: Dependable Rare with serious per-shot damage. The 13m optimal range is the defining constraint — demands extreme aggression. Outperformed by all Epic/Legendary CQ options but solid when energy budget is tight. | AC82: 235 | AD82: A-Coins | AE82: rare_weapon_10
A83: W082 | B83: Fragment Gun 12 | C83: Fragment Gun | D83: Rare | E83: Close Quarters | F83: B | G83: 12 | H83: 90 rpm | I83: 6 | J83: 6s | K83: 0–13m | L83: 32m | M83: Wide Hit Cone | N83: Shots fire in a cone, making them good at hitting fast targets or at short range. | T83: ~1,052 | U83: 1 | V83: 3 | W83: 2 | X83: 3 | Y83: 3 | Z83: Highest damage per shot of any Rare CQ weapon; wide hit cone connects reliably against mobile targets; available across five energy tiers. | AA83: 13m optimal range demands near point-blank positioning; punishes every miss; small magazine. | AB83: Dependable Rare with serious per-shot damage. The 13m optimal range is the defining constraint — demands extreme aggression. Outperformed by all Epic/Legendary CQ options but solid when energy budget is tight. | AC83: 24400 | AD83: Credits | AE83: rare_weapon_12
A84: W083 | B84: Fragment Gun 14 | C84: Fragment Gun | D84: Rare | E84: Close Quarters | F84: B | G84: 14 | H84: 90 rpm | I84: 6 | J84: 6s | K84: 0–13m | L84: 32m | M84: Wide Hit Cone | N84: Shots fire in a cone, making them good at hitting fast targets or at short range. | T84: ~1,052 | U84: 1 | V84: 3 | W84: 2 | X84: 3 | Y84: 3 | Z84: Highest damage per shot of any Rare CQ weapon; wide hit cone connects reliably against mobile targets; available across five energy tiers. | AA84: 13m optimal range demands near point-blank positioning; punishes every miss; small magazine. | AB84: Dependable Rare with serious per-shot damage. The 13m optimal range is the defining constraint — demands extreme aggression. Outperformed by all Epic/Legendary CQ options but solid when energy budget is tight. | AC84: 250 | AD84: A-Coins | AE84: rare_weapon_14
A85: W084 | B85: Fuse Mortar 8 | C85: Fuse Mortar | D85: Epic B | E85: Artillery | F85: B | G85: 8 | H85: 720 rpm | I85: 4 | J85: 13s | K85: 45–225m | L85: 225m | M85: Trip Hazard | N85: Scatters motion-sensitive Bombs over a large area that explode when enemies approach. The Bombs detonate instantly if they hit a Mech directly. If no enemies trigger the fuse, they will explode after a short time. | T85: ~1085 | U85: 4 | V85: 3 | W85: 5 | X85: 4 | Y85: 4 | Z85: Trip Hazard scatters bombs — persistent area denial; bombs detonate on direct mech contact; same 225m reach as Rocket Mortar. | AA85: 45m minimum range rules out close fights; detonation delay lets aware enemies vacate; scatter can spread damage rather than concentrate it. | AB85: Trip Hazard converts each shot into a multi-bomb scatter — four salvos can deny an entire objective zone. Higher DPS and larger blast radius than the Rocket Mortar make it the clear superior at every shared energy tier. | AC85: 825 | AD85: A-Coins | AE85: epic_b_weapon_8
A86: W085 | B86: Fuse Mortar 10 | C86: Fuse Mortar | D86: Epic B | E86: Artillery | F86: B | G86: 10 | H86: 720 rpm | I86: 4 | J86: 13s | K86: 45–225m | L86: 225m | M86: Trip Hazard | N86: Scatters motion-sensitive Bombs over a large area that explode when enemies approach. The Bombs detonate instantly if they hit a Mech directly. If no enemies trigger the fuse, they will explode after a short time. | T86: ~1085 | U86: 4 | V86: 3 | W86: 5 | X86: 4 | Y86: 4 | Z86: Trip Hazard scatters bombs — persistent area denial; bombs detonate on direct mech contact; same 225m reach as Rocket Mortar. | AA86: 45m minimum range rules out close fights; detonation delay lets aware enemies vacate; scatter can spread damage rather than concentrate it. | AB86: Trip Hazard converts each shot into a multi-bomb scatter — four salvos can deny an entire objective zone. Higher DPS and larger blast radius than the Rocket Mortar make it the clear superior at every shared energy tier. | AC86: 87000 | AD86: Credits | AE86: epic_b_weapon_10
A87: W086 | B87: Fuse Mortar 12 | C87: Fuse Mortar | D87: Epic B | E87: Artillery | F87: B | G87: 12 | H87: 720 rpm | I87: 4 | J87: 13s | K87: 45–225m | L87: 225m | M87: Trip Hazard | N87: Scatters motion-sensitive Bombs over a large area that explode when enemies approach. The Bombs detonate instantly if they hit a Mech directly. If no enemies trigger the fuse, they will explode after a short time. | T87: ~1085 | U87: 4 | V87: 3 | W87: 5 | X87: 4 | Y87: 4 | Z87: Trip Hazard scatters bombs — persistent area denial; bombs detonate on direct mech contact; same 225m reach as Rocket Mortar. | AA87: 45m minimum range rules out close fights; detonation delay lets aware enemies vacate; scatter can spread damage rather than concentrate it. | AB87: Trip Hazard converts each shot into a multi-bomb scatter — four salvos can deny an entire objective zone. Higher DPS and larger blast radius than the Rocket Mortar make it the clear superior at every shared energy tier. | AC87: 910 | AD87: A-Coins | AE87: epic_b_weapon_12
A88: W087 | B88: Fusion Cannon 6 | C88: Fusion Cannon | D88: Epic A | E88: Assault | F88: C | G88: 6 | H88: 313 rpm | I88: 25 | J88: 7.5s | K88: 0–50m | L88: 80m | M88: Fusillade | N88: Fires rapidly, dealing high damage at medium range. | T88: 593 | U88: 3 | V88: 4 | W88: 3 | X88: 4 | Y88: 2 | Z88: High damage per shot; Fusillade enables strong DPS windows; available across 5 energy tiers for flexibility. | AA88: Lowest fire rate in the assault family; small magazine; punishing reload on misses. | AB88: The Fusion Cannon punches hard per shot and Fusillade amplifies that in close-medium engagements. Available from 6 to 16 energy makes it very flexible across mech builds. The low fire rate and small mag demand precision — high reward for accurate players. | AC88: 665 | AD88: A-Coins | AE88: epic_a_weapon_6
A89: W088 | B89: Fusion Cannon 8 | C89: Fusion Cannon | D89: Epic A | E89: Assault | F89: C | G89: 8 | H89: 313 rpm | I89: 25 | J89: 7.5s | K89: 0–50m | L89: 80m | M89: Fusillade | N89: Fires rapidly, dealing high damage at medium range. | T89: 593 | U89: 3 | V89: 4 | W89: 3 | X89: 4 | Y89: 2 | Z89: High damage per shot; Fusillade enables strong DPS windows; available across 5 energy tiers for flexibility. | AA89: Lowest fire rate in the assault family; small magazine; punishing reload on misses. | AB89: The Fusion Cannon punches hard per shot and Fusillade amplifies that in close-medium engagements. Available from 6 to 16 energy makes it very flexible across mech builds. The low fire rate and small mag demand precision — high reward for accurate players. | AC89: 705 | AD89: A-Coins | AE89: epic_a_weapon_8
A90: W089 | B90: Fusion Cannon 10 | C90: Fusion Cannon | D90: Epic A | E90: Assault | F90: C | G90: 10 | H90: 313 rpm | I90: 25 | J90: 7.5s | K90: 0–50m | L90: 80m | M90: Fusillade | N90: Fires rapidly, dealing high damage at medium range. | T90: 593 | U90: 3 | V90: 4 | W90: 3 | X90: 4 | Y90: 2 | Z90: High damage per shot; Fusillade enables strong DPS windows; available across 5 energy tiers for flexibility. | AA90: Lowest fire rate in the assault family; small magazine; punishing reload on misses. | AB90: The Fusion Cannon punches hard per shot and Fusillade amplifies that in close-medium engagements. Available from 6 to 16 energy makes it very flexible across mech builds. The low fire rate and small mag demand precision — high reward for accurate players. | AC90: 73450 | AD90: Credits | AE90: epic_a_weapon_10
A91: W090 | B91: Fusion Cannon 12 | C91: Fusion Cannon | D91: Epic A | E91: Assault | F91: C | G91: 12 | H91: 313 rpm | I91: 25 | J91: 7.5s | K91: 0–50m | L91: 80m | M91: Fusillade | N91: Fires rapidly, dealing high damage at medium range. | T91: 593 | U91: 3 | V91: 4 | W91: 3 | X91: 4 | Y91: 2 | Z91: High damage per shot; Fusillade enables strong DPS windows; available across 5 energy tiers for flexibility. | AA91: Lowest fire rate in the assault family; small magazine; punishing reload on misses. | AB91: The Fusion Cannon punches hard per shot and Fusillade amplifies that in close-medium engagements. Available from 6 to 16 energy makes it very flexible across mech builds. The low fire rate and small mag demand precision — high reward for accurate players. | AC91: 760 | AD91: A-Coins | AE91: epic_a_weapon_12
A92: W091 | B92: Fusion Cannon 16 | C92: Fusion Cannon | D92: Epic A | E92: Assault | F92: C | G92: 16 | H92: 313 rpm | I92: 25 | J92: 7.5s | K92: 0–50m | L92: 80m | M92: Fusillade | N92: Fires rapidly, dealing high damage at medium range. | T92: 593 | U92: 3 | V92: 4 | W92: 3 | X92: 4 | Y92: 2 | Z92: High damage per shot; Fusillade enables strong DPS windows; available across 5 energy tiers for flexibility. | AA92: Lowest fire rate in the assault family; small magazine; punishing reload on misses. | AB92: The Fusion Cannon punches hard per shot and Fusillade amplifies that in close-medium engagements. Available from 6 to 16 energy makes it very flexible across mech builds. The low fire rate and small mag demand precision — high reward for accurate players. | AC92: 79950 | AD92: Credits | AE92: epic_a_weapon_16
A93: W092 | B93: Gauss Rifle 4 | C93: Gauss Rifle | D93: Rare | E93: Sniper | F93: D | G93: 4 | H93: 168 rpm | I93: 10 | J93: 5s | K93: 0–180m | L93: 180m | M93: Adaptable | N93: Effective at most ranges and has high ammunition. | T93: ~583 | U93: 5 | V93: 3 | W93: 2 | X93: 3 | Z93: Only sniper with 0–180m full-spectrum optimal range; most sustained fire in the sniper category; 50% Double Damage Chance; available from 4 energy. | AA93: Rare rarity caps damage ceiling; Adaptable perk is generic; lowest per-shot damage in category by a wide margin. | AB93: A versatile sniper — full-range optimal removes all positional constraints. High fire rate and Double Damage Chance generate reliable pressure no other sniper matches. Very lacking in terms of damage. | AC93: 205 | AD93: A-Coins | AE93: rare_weapon_4
A94: W093 | B94: Gauss Rifle 6 | C94: Gauss Rifle | D94: Rare | E94: Sniper | F94: D | G94: 6 | H94: 168 rpm | I94: 10 | J94: 5s | K94: 0–180m | L94: 180m | M94: Adaptable | N94: Effective at most ranges and has high ammunition. | T94: ~583 | U94: 5 | V94: 3 | W94: 2 | X94: 3 | Z94: Only sniper with 0–180m full-spectrum optimal range; most sustained fire in the sniper category; 50% Double Damage Chance; available from 4 energy. | AA94: Rare rarity caps damage ceiling; Adaptable perk is generic; lowest per-shot damage in category by a wide margin. | AB94: A versatile sniper — full-range optimal removes all positional constraints. High fire rate and Double Damage Chance generate reliable pressure no other sniper matches. Very lacking in terms of damage. | AC94: 220 | AD94: A-Coins | AE94: rare_weapon_6
A95: W094 | B95: Gauss Rifle 10 | C95: Gauss Rifle | D95: Rare | E95: Sniper | F95: D | G95: 10 | H95: 168 rpm | I95: 10 | J95: 5s | K95: 0–180m | L95: 180m | M95: Adaptable | N95: Effective at most ranges and has high ammunition. | T95: ~583 | U95: 5 | V95: 3 | W95: 2 | X95: 3 | Z95: Only sniper with 0–180m full-spectrum optimal range; most sustained fire in the sniper category; 50% Double Damage Chance; available from 4 energy. | AA95: Rare rarity caps damage ceiling; Adaptable perk is generic; lowest per-shot damage in category by a wide margin. | AB95: A versatile sniper — full-range optimal removes all positional constraints. High fire rate and Double Damage Chance generate reliable pressure no other sniper matches. Very lacking in terms of damage. | AC95: 235 | AD95: A-Coins | AE95: rare_weapon_10
A96: W095 | B96: Gemini 6 | C96: Gemini | D96: Legendary | E96: Guided | F96: S | G96: 6 | H96: 16 rpm | I96: 2 | J96: 6s | K96: 0–170m | L96: 170m | M96: Duality Shot | N96: Fires two tracking rockets. The first applies Weaken; the second applies Stasis. | O96: Weakens from shot 1, +50% dmg | T96: ~492 | U96: 5 | V96: 4 | W96: 5 | X96: 4 | Z96: First rocket applies Weaken — second rocket deals 1.5× damage on the weakened target; Stasis on second rocket locks the target; 170m range — longest in guided; rockets chase targets; 30% Double Damage Chance. | AA96: Lowest base fire rate of any guided weapon; slow projectile speed gives enemies time to find hard cover. | AB96: Range and CC king. Weaken-into-Stasis at 170m is a kill setup for allied snipers from positions no other guided weapon reaches. The Weaken boost means the second rocket hits for 50% more, making the two-rocket volley punch well above its listed damage. S-tier alongside Savant: Savant for multi-target sustained, Gemini for single-target CC at extreme range. | AC96: 600000 | AD96: Credits | AE96: legendary_weapon_6
A97: W096 | B97: Gemini 8 | C97: Gemini | D97: Legendary | E97: Guided | F97: S | G97: 8 | H97: 16 rpm | I97: 2 | J97: 6s | K97: 0–170m | L97: 170m | M97: Duality Shot | N97: Fires two tracking rockets. The first applies Weaken; the second applies Stasis. | O97: Weakens from shot 1, +50% dmg | T97: ~492 | U97: 5 | V97: 4 | W97: 5 | X97: 4 | Z97: First rocket applies Weaken — second rocket deals 1.5× damage on the weakened target; Stasis on second rocket locks the target; 170m range — longest in guided; rockets chase targets; 30% Double Damage Chance. | AA97: Lowest base fire rate of any guided weapon; slow projectile speed gives enemies time to find hard cover. | AB97: Range and CC king. Weaken-into-Stasis at 170m is a kill setup for allied snipers from positions no other guided weapon reaches. The Weaken boost means the second rocket hits for 50% more, making the two-rocket volley punch well above its listed damage. S-tier alongside Savant: Savant for multi-target sustained, Gemini for single-target CC at extreme range. | AC97: 8275 | AD97: A-Coins | AE97: legendary_weapon_8
A98: W097 | B98: Gemini 10 | C98: Gemini | D98: Legendary | E98: Guided | F98: S | G98: 10 | H98: 16 rpm | I98: 2 | J98: 6s | K98: 0–170m | L98: 170m | M98: Duality Shot | N98: Fires two tracking rockets. The first applies Weaken; the second applies Stasis. | O98: Weakens from shot 1, +50% dmg | T98: ~492 | U98: 5 | V98: 4 | W98: 5 | X98: 4 | Z98: First rocket applies Weaken — second rocket deals 1.5× damage on the weakened target; Stasis on second rocket locks the target; 170m range — longest in guided; rockets chase targets; 30% Double Damage Chance. | AA98: Lowest base fire rate of any guided weapon; slow projectile speed gives enemies time to find hard cover. | AB98: Range and CC king. Weaken-into-Stasis at 170m is a kill setup for allied snipers from positions no other guided weapon reaches. The Weaken boost means the second rocket hits for 50% more, making the two-rocket volley punch well above its listed damage. S-tier alongside Savant: Savant for multi-target sustained, Gemini for single-target CC at extreme range. | AC98: 712500 | AD98: Credits | AE98: legendary_weapon_10
A99: W098 | B99: Gemini 12 | C99: Gemini | D99: Legendary | E99: Guided | F99: S | G99: 12 | H99: 16 rpm | I99: 2 | J99: 6s | K99: 0–170m | L99: 170m | M99: Duality Shot | N99: Fires two tracking rockets. The first applies Weaken; the second applies Stasis. | O99: Weakens from shot 1, +50% dmg | T99: ~492 | U99: 5 | V99: 4 | W99: 5 | X99: 4 | Z99: First rocket applies Weaken — second rocket deals 1.5× damage on the weakened target; Stasis on second rocket locks the target; 170m range — longest in guided; rockets chase targets; 30% Double Damage Chance. | AA99: Lowest base fire rate of any guided weapon; slow projectile speed gives enemies time to find hard cover. | AB99: Range and CC king. Weaken-into-Stasis at 170m is a kill setup for allied snipers from positions no other guided weapon reaches. The Weaken boost means the second rocket hits for 50% more, making the two-rocket volley punch well above its listed damage. S-tier alongside Savant: Savant for multi-target sustained, Gemini for single-target CC at extreme range. | AC99: 7500 | AD99: A-Coins | AE99: legendary_weapon_12
A100: W099 | B100: Gemini 16 | C100: Gemini | D100: Legendary | E100: Guided | F100: S | G100: 16 | H100: 16 rpm | I100: 2 | J100: 6s | K100: 0–170m | L100: 170m | M100: Duality Shot | N100: Fires two tracking rockets. The first applies Weaken; the second applies Stasis. | O100: Weakens from shot 1, +50% dmg | T100: ~492 | U100: 5 | V100: 4 | W100: 5 | X100: 4 | Z100: First rocket applies Weaken — second rocket deals 1.5× damage on the weakened target; Stasis on second rocket locks the target; 170m range — longest in guided; rockets chase targets; 30% Double Damage Chance. | AA100: Lowest base fire rate of any guided weapon; slow projectile speed gives enemies time to find hard cover. | AB100: Range and CC king. Weaken-into-Stasis at 170m is a kill setup for allied snipers from positions no other guided weapon reaches. The Weaken boost means the second rocket hits for 50% more, making the two-rocket volley punch well above its listed damage. S-tier alongside Savant: Savant for multi-target sustained, Gemini for single-target CC at extreme range. | AC100: 8275 | AD100: A-Coins | AE100: legendary_weapon_16
...

Sheet Weapon Upgrade Costs
A1: Rarity Key | B1: Star | C1: Level | D1: Credits | E1: A-Coins | F1: Blueprints | G1: Step
A2: common_weapon_2 | B2: 1 | C2: 1 | D2: 25 | E2: 0 | F2: 0 | G2: =(B2-1)*7+C2
A3: common_weapon_4 | B3: 1 | C3: 1 | D3: 50 | E3: 0 | F3: 0 | G3: =(B3-1)*7+C3
A4: common_weapon_6 | B4: 1 | C4: 1 | D4: 50 | E4: 0 | F4: 0 | G4: =(B4-1)*7+C4
A5: epic_a_weapon_10 | B5: 1 | C5: 1 | D5: 0 | E5: 0 | F5: 0 | G5: =(B5-1)*7+C5
A6: epic_a_weapon_12 | B6: 1 | C6: 1 | D6: 0 | E6: 0 | F6: 0 | G6: =(B6-1)*7+C6
A7: epic_a_weapon_14 | B7: 1 | C7: 1 | D7: 0 | E7: 0 | F7: 0 | G7: =(B7-1)*7+C7
A8: epic_a_weapon_16 | B8: 1 | C8: 1 | D8: 0 | E8: 0 | F8: 0 | G8: =(B8-1)*7+C8
A9: epic_a_weapon_6 | B9: 1 | C9: 1 | D9: 0 | E9: 0 | F9: 0 | G9: =(B9-1)*7+C9
A10: epic_a_weapon_8 | B10: 1 | C10: 1 | D10: 0 | E10: 0 | F10: 0 | G10: =(B10-1)*7+C10
A11: epic_b_weapon_10 | B11: 1 | C11: 1 | D11: 0 | E11: 0 | F11: 0 | G11: =(B11-1)*7+C11
A12: epic_b_weapon_12 | B12: 1 | C12: 1 | D12: 0 | E12: 0 | F12: 0 | G12: =(B12-1)*7+C12
A13: epic_b_weapon_16 | B13: 1 | C13: 1 | D13: 0 | E13: 0 | F13: 0 | G13: =(B13-1)*7+C13
... A1555: uncommon_weapon_8 | B1555: 6 | C1555: 7 | D1555: 0 | E1555: 0 | F1555: 0 | G1555: =(B1555-1)*7+C1555

Sheet Pilots
A1: Pilot ID | B1: Name | C1: Rarity | D1: Skill / Weapon Type | E1: Weapon 2 | F1: Max HP Bonus % | G1: Max DMG Bonus % | H1: Unlock Cost | I1: Unlock Currency | J1: Source | K1: Last Updated | L1: Verified
A2: P001 | B2: Acantha | C2: Epic | D2: Assault | E2: None | F2: 25 | G2: 49 | H2: 0 | I2: Paid | J2: Krishna | K2: 46097 | L2: Verified
A3: P002 | B3: Archangel | C3: Legendary | D3: Sniper | E3: None | F3: 40 | G3: 70 | H3: 3840 | I3: A coins | J3: Krishna | K3: 46110 | L3: Verified
A4: P003 | B4: Asami | C4: Legendary | D4: Beam | E4: None | F4: 40 | G4: 70 | H4: 3840 | I4: A coins | J4: Krishna | K4: 46106 | L4: Verified
A5: P004 | B5: Asmodeus | C5: Legendary | D5: Heavy duty | E5: None | F5: 40 | G5: 70 | H5: 3840 | I5: A coins | J5: Krishna | K5: 46130 | L5: Verified
A6: P005 | B6: Baron | C6: Legendary | D6: Sniper | E6: None | F6: 40 | G6: 70 | H6: 3840 | I6: A coins | J6: Krishna | K6: 46111 | L6: Verified
A7: P006 | B7: Boar | C7: Legendary | D7: Artillery | E7: None | F7: 40 | G7: 70 | H7: 3840 | I7: A coins | J7: Krishna | K7: 46119 | L7: Verified
A8: P007 | B8: Case | C8: Epic | D8: Heavy duty | E8: None | F8: 25 | G8: 49 | H8: 1040 | I8: A coins | J8: Krishna | K8: 46129 | L8: Verified
A9: P008 | B9: Chimera | C9: Legendary | D9: Heavy duty | E9: None | F9: 40 | G9: 70 | H9: 3840 | I9: A coins | J9: Krishna | K9: 46131 | L9: Verified
A10: P009 | B10: Crow | C10: Rare | D10: Guided | E10: None | F10: 17 | G10: 29 | H10: 40000 | I10: Credits | J10: Krishna | K10: 46113 | L10: Verified
A11: P010 | B11: Diesel | C11: Legendary | D11: Missile | E11: None | F11: 40 | G11: 70 | H11: 3840 | I11: A coins | J11: Krishna | K11: 46102 | L11: Verified
A12: P011 | B12: Fei | C12: Epic | D12: Artillery | E12: None | F12: 25 | G12: 49 | H12: 1040 | I12: A coins | J12: Krishna | K12: 46118 | L12: Verified
A13: P012 | B13: Galvan | C13: Legendary | D13: Close quarters | E13: None | F13: 40 | G13: 70 | H13: $ | I13: Paid | J13: Krishna | K13: 46125 | L13: Verified
A14: P013 | B14: G Lock | C14: Epic | D14: Close quarters | E14: None | H14: 1040 | I14: A coins | L14: Pending
A15: P014 | B15: Impulse | C15: Epic | D15: Barrage | E15: None | F15: 25 | G15: 49 | H15: 1040 | I15: A coins | J15: Krishna | K15: 46126 | L15: Verified
A16: P015 | B16: Ingrid | C16: Legendary | D16: Beam | E16: None | F16: 40 | G16: 70 | H16: 3840 | I16: A coins | J16: Krishna | K16: 46107 | L16: Verified
A17: P016 | B17: Jester | C17: Rare | D17: Close quarters | E17: None | F17: 17 | G17: 29 | H17: 40000 | I17: Credits | J17: Krishna | K17: 46121 | L17: Verified
A18: P017 | B18: Lodestar | C18: Legendary | D18: Barrage | E18: None | F18: 40 | G18: 70 | H18: 3840 | I18: A coins | J18: Krishna | K18: 46127 | L18: Verified
A19: P018 | B19: Major | C19: Legendary | D19: Assault | E19: None | F19: 40 | G19: 70 | H19: 3840 | I19: A coins | J19: Krishna | K19: 46098 | L19: Verified
A20: P019 | B20: Mako | C20: Rare | D20: Beam | E20: None | F20: 17 | G20: 29 | H20: 40000 | I20: Credits | J20: Krishna | K20: 46104 | L20: Verified
A21: P020 | B21: Maverick | C21: Epic | D21: Sniper | E21: None | F21: 25 | G21: 49 | H21: 1040 | I21: A coins | J21: Krishna | K21: 46109 | L21: Verified
A22: P021 | B22: Morpho | C22: Legendary | D22: Sniper | E22: None | F22: 40 | G22: 70 | H22: $ | I22: Paid | J22: Krishna | K22: 46112 | L22: Verified
A23: P022 | B23: Myna | C23: Legendary | D23: Close quarters | E23: None | F23: 40 | G23: 70 | H23: 3840 | I23: A coins | J23: Krishna | K23: 46123 | L23: Verified
A24: P023 | B24: Neev | C24: Legendary | D24: Close quarters | E24: None | F24: 40 | G24: 70 | H24: 3840 | I24: A coins | J24: Krishna | K24: 46124 | L24: Verified
A25: P024 | B25: Nicklas | C25: Legendary | D25: Missile | E25: None | F25: 40 | G25: 70 | H25: 3840 | I25: A coins | J25: Krishna | K25: 46103 | L25: Verified
A26: P025 | B26: Nova | C26: Epic | D26: Missile | E26: None | F26: 25 | G26: 49 | H26: 1040 | I26: A coins | J26: Krishna | K26: 46101 | L26: Verified
A27: P026 | B27: Red | C27: Rare | D27: Assault | E27: None | F27: 17 | G27: 29 | H27: 40000 | I27: Credits | J27: Krishna | K27: 46096 | L27: Verified
A28: P027 | B28: Rosa | C28: Epic | D28: Guided | E28: None | F28: 25 | G28: 49 | H28: 1040 | I28: A coins | J28: Krishna | K28: 46114 | L28: Verified
A29: P028 | B29: Samson | C29: Rare | D29: Missile | E29: None | F29: 17 | G29: 29 | H29: 40000 | I29: Credits | J29: Krishna | K29: 46100 | L29: Verified
A30: P029 | B30: Spark | C30: Rare | D30: Artillery | E30: None | F30: 17 | G30: 29 | H30: 40000 | I30: Credits | J30: Krishna | K30: 46117 | L30: Verified
A31: P030 | B31: Stefania | C31: Legendary | D31: Guided | E31: None | F31: 40 | G31: 70 | H31: 3840 | I31: A coins | J31: Krishna | K31: 46115 | L31: Verified
A32: P031 | B32: Sunny | C32: Legendary | D32: Assault | E32: None | F32: 40 | G32: 70 | H32: 3840 | I32: A coins | J32: Krishna | K32: 46099 | L32: Verified
A33: P032 | B33: Targe | C33: Legendary | D33: Artillery | E33: None | F33: 40 | G33: 70 | H33: $ | I33: Paid | J33: Krishna | K33: 46120 | L33: Verified
A34: P033 | B34: Torchlight | C34: Rare | D34: Sniper | E34: None | F34: 17 | G34: 29 | H34: 40000 | I34: Credits | J34: Krishna | K34: 46108 | L34: Verified
A35: P034 | B35: Val | C35: Legendary | D35: Barrage | E35: None | F35: 40 | G35: 70 | H35: 3840 | I35: A coins | J35: Krishna | K35: 46128 | L35: Verified
A36: P035 | B36: Vox | C36: Legendary | D36: Guided | E36: None | F36: 40 | G36: 70 | H36: 3840 | I36: A coins | J36: Krishna | K36: 46116 | L36: Verified
A37: P036 | B37: Yeti | C37: Epic | D37: Beam | E37: None | F37: 25 | G37: 49 | H37: 1040 | I37: A coins | J37: Krishna | K37: 46105 | L37: Verified

Sheet Pilot Upgrade Costs
A1: Rarity | B1: Star | C1: Level | D1: A-Coins | E1: Marks | F1: XP | G1: Step
A2: rare | B2: 1 | C2: 1 | D2: 6 | E2: 0 | F2: 570 | G2: =(B2-1)*7+C2
A3: epic | B3: 1 | C3: 1 | D3: 8 | E3: 0 | F3: 800 | G3: =(B3-1)*7+C3
A4: legendary | B4: 1 | C4: 1 | D4: 12 | E4: 0 | F4: 1140 | G4: =(B4-1)*7+C4
A5: rare | B5: 1 | C5: 2 | D5: 7 | E5: 0 | F5: 650 | G5: =(B5-1)*7+C5
A6: epic | B6: 1 | C6: 2 | D6: 10 | E6: 0 | F6: 905 | G6: =(B6-1)*7+C6
A7: legendary | B7: 1 | C7: 2 | D7: 14 | E7: 0 | F7: 1295 | G7: =(B7-1)*7+C7
A8: rare | B8: 1 | C8: 3 | D8: 9 | E8: 0 | F8: 740 | G8: =(B8-1)*7+C8
A9: epic | B9: 1 | C9: 3 | D9: 12 | E9: 0 | F9: 1035 | G9: =(B9-1)*7+C9
A10: legendary | B10: 1 | C10: 3 | D10: 17 | E10: 0 | F10: 1475 | G10: =(B10-1)*7+C10
A11: rare | B11: 1 | C11: 4 | D11: 10 | E11: 0 | F11: 840 | G11: =(B11-1)*7+C11
A12: epic | B12: 1 | C12: 4 | D12: 14 | E12: 0 | F12: 1175 | G12: =(B12-1)*7+C12
A13: legendary | B13: 1 | C13: 4 | D13: 20 | E13: 0 | F13: 1675 | G13: =(B13-1)*7+C13
... A127: legendary | B127: 6 | C127: 7 | D127: 0 | E127: 0 | F127: 0 | G127: =(B127-1)*7+C127

Sheet Mods
A1: Mod ID | B1: Name | C1: Mod Key | D1: Rarity | E1: Max Bonus % | F1: Effect Description | G1: Purchase Cost | H1: Purchase Currency | I1: Source | J1: Last Updated | K1: Verified | L1: Cost Table Key
A2: MOD001 | B2: Perimeter ML | C2: perimeter_ml | D2: Epic | E2: 10 | F2: Grants the Mech a Multi-layered, ring-shaped shield when it spawns. | G2: 380 | H2: basic_mod_parts | I2: Krishna | J2: 46089 | K2: Verified | L2: epic_perimeter_ml
A3: MOD002 | B3: Blockade ML | C3: blockade_ml | D3: Epic | E3: 13 | F3: Grants the Mech a multi-layered, front-facing shield when it spawns | G3: 615 | H3: basic_mod_parts | I3: Krishna | J3: 46093 | K3: Verified | L3: epic_blockade_ml
A4: MOD003 | B4: Perimeter | C4: perimeter | D4: Epic | G4: 2945 | H4: basic_mod_parts | K4: Pending | L4: epic_perimeter
A5: MOD004 | B5: Blockade | C5: blockade | D5: Epic | G5: 3825 | H5: basic_mod_parts | K5: Pending | L5: epic_blockade
A6: MOD005 | B6: Hardened hull | C6: hardened_hull | D6: Epic | G6: 1480 | H6: basic_mod_parts | K6: Pending | L6: epic_hardened_hull
A7: MOD006 | B7: Canopy | C7: canopy | D7: Epic | G7: 1480 | H7: basic_mod_parts | K7: Pending | L7: epic_canopy
A8: MOD007 | B8: Galvanic Hull | C8: galvanic_hull | D8: Epic | G8: 2360 | H8: basic_mod_parts | K8: Pending | L8: epic_galvanic_hull
A9: MOD008 | B9: Perimeter ML | C9: perimeter_ml | D9: Legendary | E9: 10 | F9: Grants the Mech a Multi-layered, ring-shaped shield when it spawns. | G9: 115 | H9: elite_mod_parts | I9: Krishna | J9: 46089 | K9: Verified | L9: legendary_perimeter_ml
A10: MOD009 | B10: Blockade ML | C10: blockade_ml | D10: Legendary | E10: 13 | F10: Grants the Mech a multi-layered, front-facing shield when it spawns | G10: 300 | H10: elite_mod_parts | I10: Krishna | J10: 46093 | K10: Verified | L10: legendary_blockade_ml
A11: MOD010 | B11: Perimeter | C11: perimeter | D11: Legendary | G11: 1175 | H11: elite_mod_parts | K11: Pending | L11: legendary_perimeter
A12: MOD011 | B12: Blockade | C12: blockade | D12: Legendary | G12: 1575 | H12: elite_mod_parts | K12: Pending | L12: legendary_blockade
A13: MOD012 | B13: Hardened hull | C13: hardened_hull | D13: Legendary | G13: 600 | H13: elite_mod_parts | K13: Pending | L13: legendary_hardened_hull
A14: MOD013 | B14: Canopy | C14: canopy | D14: Legendary | G14: 660 | H14: elite_mod_parts | K14: Pending | L14: legendary_canopy
A15: MOD014 | B15: Galvanic Hull | C15: galvanic_hull | D15: Legendary | G15: 1030 | H15: elite_mod_parts | K15: Pending | L15: legendary_galvanic_hull

Sheet Mod Upgrade Costs
A1: Cost Table Key | B1: Level | C1: Basic Mod Parts | D1: Elite Mod Parts
A2: epic_blockade | B2: 2 | C2: 590 | D2: 0
A3: epic_blockade_ml | B3: 2 | C3: 360 | D3: 0
A4: epic_canopy | B4: 2 | C4: 300 | D4: 0
A5: epic_galvanic_hull | B5: 2 | C5: 590 | D5: 0
A6: epic_hardened_hull | B6: 2 | C6: 300 | D6: 0
A7: epic_perimeter | B7: 2 | C7: 300 | D7: 0
A8: epic_perimeter_ml | B8: 2 | C8: 130 | D8: 0
A9: legendary_blockade | B9: 2 | C9: 2350 | D9: 0
A10: legendary_blockade_ml | B10: 2 | C10: 1195 | D10: 0
A11: legendary_canopy | B11: 2 | C11: 885 | D11: 0
A12: legendary_galvanic_hull | B12: 2 | C12: 1470 | D12: 0
A13: legendary_hardened_hull | B13: 2 | C13: 970 | D13: 0
... A71: legendary_perimeter_ml | B71: 6 | C71: 0 | D71: 815

Sheet Best Builds
A1: # | B1: Mech Name | C1: Weapon 1 | D1: W1 Energy | E1: Weapon 2 | F1: W2 Energy | G1: Total Energy
A2: 1 | B2: Deathwalker | C2: Storm Rack | D2: 10 | E2: Storm Rack | F2: 10
A3: 2 | B3: Redox | C3: Hornet | D3: 12 | E3: Hornet | F3: 12
A4: 3 | B4: Deathwalker | C4: Repeater | D4: 10 | E4: Repeater | F4: 10
A5: 4 | B5: Deathwalker | C5: Storm Rack | D5: 16 | E5: Storm Rack | F5: 6
A6: 5 | B6: Mimicker | C6: Savant | D6: 16 | E6: Savant | F6: 8
A7: 6 | B7: Mimicker | C7: Storm Rack | D7: 16 | E7: Storm Rack | F7: 8
A8: 7 | B8: Mimicker | C8: Savant | D8: 12 | E8: Savant | F8: 12
A9: 8 | B9: Mimicker | C9: Storm Rack | D9: 12 | E9: Storm Rack | F9: 12
A10: 9 | B10: Mimicker | C10: Storm Rack | D10: 16 | E10: Storm Rack | F10: 6
A11: 10 | B11: Deathwalker | C11: Overdriver | D11: 10 | E11: Overdriver | F11: 10
A12: 11 | B12: Orion | C12: Gemini | D12: 10 | E12: Gemini | F12: 6
A13: 12 | B13: Orion | C13: Gemini | D13: 10 | E13: Gemini | F13: 10
... A78: 77 | B78: Blizzfrost | C78: Compound Beam | D78: 12 | E78: Compound Beam | F78: 12
A79: 78
A80: 79
A81: 80
A82: 81
A83: 82
A84: 83
A85: 84
A86: 85
A87: 86
A88: 87
A89: 88
A90: 89
... A101: 100

Sheet Meta
A1: Rank | B1: Mech Name | C1: Weapon 1 | D1: W1 Energy | E1: Weapon 2 | F1: W2 Energy | G1: Total Energy
A2: 🥇 1 | B2: Deathwalker | C2: Strike Rocket | D2: 16 | E2: Storm Rack | F2: 16
A3: 🥈 2 | B3: Outlaw | C3: Storm Rack | D3: 16 | E3: Storm Rack | F3: 16
A4: 🥉 3 | B4: Outlaw | C4: Charge Rocket | D4: 16 | E4: Charge Rocket | F4: 16
A5: 4 | B5: Lacewing | C5: Storm Rack | D5: 12 | E5: Storm Rack | F5: 12
A6: 5 | B6: Tailsting | C6: Burrow Beam | D6: 12 | E6: Burrow Beam | F6: 12
A7: 6 | B7: Citadel | C7: Compound Beam | D7: 12 | E7: Compound Beam | F7: 12
A8: 7 | B8: Blizzfrost | C8: Compound Beam | D8: 12 | E8: Compound Beam | F8: 12
A9: 8 | B9: Citadel | C9: Revoker | D9: 12 | E9: Revoker | F9: 12
A10: 9 | B10: Deathwalker | C10: Charge Rocket | D10: 16 | E10: Charge Rocket | F10: 16
A11: 10 | B11: Surge | C11: Revoker | D11: 12 | E11: Revoker | F11: 12
A12: 11
A13: 12
A14: 13
A15: 14
A16: 15
A17: 16
A18: 17
A19: 18
A20: 19
A21: 20
